Workbook

Sheet Synthèse
A1: VITRACO Moto — Plan de test du jalon V1
A2: Lot 1 « Stock et logistique » · document de recette · version du 18 octobre 2026
A4: 1. Objet et conditions de passage
A5: Le jalon V1 correspond au Lot 1 « Stock et logistique » du plan de livraison (SRS 13.4). Condition de mise en service : « Stock initial importé par châssis et rapproché par scan au magasin et dans les boutiques ». Ce classeur contient les cas de test à jouer à la main, les scénarios de recette de bout en bout, la checklist de reprise des données, la traçabilité vers les user stories, et le suivi des anomalies.
A6: Périmètre : sprints S1 (socle et catalogue), S2 (importation et réception par scan) et S3 (stock, transferts) : US-001 à 008, 010 à 013, 020 à 027, 040 à 046 et 155, avec les modules ADM, CAT, APP, REC, STK, TRF, l'import du stock initial et le rapprochement par pointage.
A7: Les scénarios R1 (partie réception), R6 et R10 (partie droits) du SRS 14.1 sont repris dans l'onglet « Recette Lot 1 ». Les scénarios R2 à R5, R7 à R9, R11 et R12 relèvent des lots 2 à 4.
A9: 2. Avancement (calculé à partir de l'onglet « Plan de test »)
A10: Cas de test au plan | B10: =COUNTA('Plan de test'!$A$5:$A$152)
A11: Cas à jouer (livrés ou partiels) | B11: =COUNTA('Plan de test'!$A$5:$A$152)-COUNTIF('Plan de test'!$M$5:$M$152,"Non livré")-COUNTIF('Plan de test'!$M$5:$M$152,"Non applicable")
A12: Réussis | B12: =COUNTIF('Plan de test'!$M$5:$M$152,"Réussi")
A13: En échec | B13: =COUNTIF('Plan de test'!$M$5:$M$152,"Échec")
A14: Bloqués | B14: =COUNTIF('Plan de test'!$M$5:$M$152,"Bloqué")
A15: Restant à tester | B15: =COUNTIF('Plan de test'!$M$5:$M$152,"À tester")
A16: Non livrés (à rejouer plus tard) | B16: =COUNTIF('Plan de test'!$M$5:$M$152,"Non livré")
A17: Taux d'exécution | B17: =IF(B11=0,0,(B12+B13+B14)/B11)
A18: Taux de réussite (sur cas exécutés) | B18: =IF((B12+B13+B14)=0,0,B12/(B12+B13+B14))
A20: 3. Avancement par module
A21: Module | B21: Cas | C21: À tester | D21: Réussis | E21: Échecs | F21: Bloqués | G21: Non livrés | H21: % réussi
A22: ADM Administration | B22: =COUNTIF('Plan de test'!$B$5:$B$152,A22) | C22: =COUNTIFS('Plan de test'!$B$5:$B$152,A22,'Plan de test'!$M$5:$M$152,"À tester") | D22: =COUNTIFS('Plan de test'!$B$5:$B$152,A22,'Plan de test'!$M$5:$M$152,"Réussi") | E22: =COUNTIFS('Plan de test'!$B$5:$B$152,A22,'Plan de test'!$M$5:$M$152,"Échec") | F22: =COUNTIFS('Plan de test'!$B$5:$B$152,A22,'Plan de test'!$M$5:$M$152,"Bloqué") | G22: =COUNTIFS('Plan de test'!$B$5:$B$152,A22,'Plan de test'!$M$5:$M$152,"Non livré") | H22: =IF(B22-G22=0,0,D22/(B22-G22))
A23: CAT Catalogue et châssis | B23: =COUNTIF('Plan de test'!$B$5:$B$152,A23) | C23: =COUNTIFS('Plan de test'!$B$5:$B$152,A23,'Plan de test'!$M$5:$M$152,"À tester") | D23: =COUNTIFS('Plan de test'!$B$5:$B$152,A23,'Plan de test'!$M$5:$M$152,"Réussi") | E23: =COUNTIFS('Plan de test'!$B$5:$B$152,A23,'Plan de test'!$M$5:$M$152,"Échec") | F23: =COUNTIFS('Plan de test'!$B$5:$B$152,A23,'Plan de test'!$M$5:$M$152,"Bloqué") | G23: =COUNTIFS('Plan de test'!$B$5:$B$152,A23,'Plan de test'!$M$5:$M$152,"Non livré") | H23: =IF(B23-G23=0,0,D23/(B23-G23))
A24: APP Approvisionnements | B24: =COUNTIF('Plan de test'!$B$5:$B$152,A24) | C24: =COUNTIFS('Plan de test'!$B$5:$B$152,A24,'Plan de test'!$M$5:$M$152,"À tester") | D24: =COUNTIFS('Plan de test'!$B$5:$B$152,A24,'Plan de test'!$M$5:$M$152,"Réussi") | E24: =COUNTIFS('Plan de test'!$B$5:$B$152,A24,'Plan de test'!$M$5:$M$152,"Échec") | F24: =COUNTIFS('Plan de test'!$B$5:$B$152,A24,'Plan de test'!$M$5:$M$152,"Bloqué") | G24: =COUNTIFS('Plan de test'!$B$5:$B$152,A24,'Plan de test'!$M$5:$M$152,"Non livré") | H24: =IF(B24-G24=0,0,D24/(B24-G24))
A25: REC Réceptions | B25: =COUNTIF('Plan de test'!$B$5:$B$152,A25) | C25: =COUNTIFS('Plan de test'!$B$5:$B$152,A25,'Plan de test'!$M$5:$M$152,"À tester") | D25: =COUNTIFS('Plan de test'!$B$5:$B$152,A25,'Plan de test'!$M$5:$M$152,"Réussi") | E25: =COUNTIFS('Plan de test'!$B$5:$B$152,A25,'Plan de test'!$M$5:$M$152,"Échec") | F25: =COUNTIFS('Plan de test'!$B$5:$B$152,A25,'Plan de test'!$M$5:$M$152,"Bloqué") | G25: =COUNTIFS('Plan de test'!$B$5:$B$152,A25,'Plan de test'!$M$5:$M$152,"Non livré") | H25: =IF(B25-G25=0,0,D25/(B25-G25))
A26: STK Stock | B26: =COUNTIF('Plan de test'!$B$5:$B$152,A26) | C26: =COUNTIFS('Plan de test'!$B$5:$B$152,A26,'Plan de test'!$M$5:$M$152,"À tester") | D26: =COUNTIFS('Plan de test'!$B$5:$B$152,A26,'Plan de test'!$M$5:$M$152,"Réussi") | E26: =COUNTIFS('Plan de test'!$B$5:$B$152,A26,'Plan de test'!$M$5:$M$152,"Échec") | F26: =COUNTIFS('Plan de test'!$B$5:$B$152,A26,'Plan de test'!$M$5:$M$152,"Bloqué") | G26: =COUNTIFS('Plan de test'!$B$5:$B$152,A26,'Plan de test'!$M$5:$M$152,"Non livré") | H26: =IF(B26-G26=0,0,D26/(B26-G26))
A27: TRF Transferts | B27: =COUNTIF('Plan de test'!$B$5:$B$152,A27) | C27: =COUNTIFS('Plan de test'!$B$5:$B$152,A27,'Plan de test'!$M$5:$M$152,"À tester") | D27: =COUNTIFS('Plan de test'!$B$5:$B$152,A27,'Plan de test'!$M$5:$M$152,"Réussi") | E27: =COUNTIFS('Plan de test'!$B$5:$B$152,A27,'Plan de test'!$M$5:$M$152,"Échec") | F27: =COUNTIFS('Plan de test'!$B$5:$B$152,A27,'Plan de test'!$M$5:$M$152,"Bloqué") | G27: =COUNTIFS('Plan de test'!$B$5:$B$152,A27,'Plan de test'!$M$5:$M$152,"Non livré") | H27: =IF(B27-G27=0,0,D27/(B27-G27))
A28: REP Reprise du stock | B28: =COUNTIF('Plan de test'!$B$5:$B$152,A28) | C28: =COUNTIFS('Plan de test'!$B$5:$B$152,A28,'Plan de test'!$M$5:$M$152,"À tester") | D28: =COUNTIFS('Plan de test'!$B$5:$B$152,A28,'Plan de test'!$M$5:$M$152,"Réussi") | E28: =COUNTIFS('Plan de test'!$B$5:$B$152,A28,'Plan de test'!$M$5:$M$152,"Échec") | F28: =COUNTIFS('Plan de test'!$B$5:$B$152,A28,'Plan de test'!$M$5:$M$152,"Bloqué") | G28: =COUNTIFS('Plan de test'!$B$5:$B$152,A28,'Plan de test'!$M$5:$M$152,"Non livré") | H28: =IF(B28-G28=0,0,D28/(B28-G28))
A29: TRV Transverse | B29: =COUNTIF('Plan de test'!$B$5:$B$152,A29) | C29: =COUNTIFS('Plan de test'!$B$5:$B$152,A29,'Plan de test'!$M$5:$M$152,"À tester") | D29: =COUNTIFS('Plan de test'!$B$5:$B$152,A29,'Plan de test'!$M$5:$M$152,"Réussi") | E29: =COUNTIFS('Plan de test'!$B$5:$B$152,A29,'Plan de test'!$M$5:$M$152,"Échec") | F29: =COUNTIFS('Plan de test'!$B$5:$B$152,A29,'Plan de test'!$M$5:$M$152,"Bloqué") | G29: =COUNTIFS('Plan de test'!$B$5:$B$152,A29,'Plan de test'!$M$5:$M$152,"Non livré") | H29: =IF(B29-G29=0,0,D29/(B29-G29))
A30: Total | B30: =SUM(B22:B29) | C30: =SUM(C22:C29) | D30: =SUM(D22:D29) | E30: =SUM(E22:E29) | F30: =SUM(F22:F29) | G30: =SUM(G22:G29) | H30: =IF(B30-G30=0,0,D30/(B30-G30))
A32: 4. Critères de sortie du jalon (go / no-go)
A33: Critère | B33: État | C33: Précision
A34: Tous les cas « Doit » livrés sont réussis | B34: =IF(COUNTIFS('Plan de test'!$J$5:$J$152,"M",'Plan de test'!$K$5:$K$152,"<>À livrer",'Plan de test'!$M$5:$M$152,"<>Réussi")=0,"OK","À faire") | C34: Les cas partiels sont jugés sur ce qui est livré ; l'écart est consigné dans les limites connues.
A35: Aucun cas en échec ni bloqué | B35: =IF(COUNTIF('Plan de test'!$M$5:$M$152,"Échec")+COUNTIF('Plan de test'!$M$5:$M$152,"Bloqué")=0,"OK","À faire") | C35: Chaque échec ouvre une anomalie dans l'onglet « Anomalies ».
A36: Aucune anomalie bloquante ou majeure ouverte | B36: =IF(COUNTIFS(Anomalies!$D$5:$D$300,"Bloquante",Anomalies!$G$5:$G$300,"<>Fermée")+COUNTIFS(Anomalies!$D$5:$D$300,"Majeure",Anomalies!$G$5:$G$300,"<>Fermée")=0,"OK","À faire") | C36: Seules des anomalies mineures peuvent rester ouvertes, avec un plan de correction.
A37: Stock d'ouverture rapproché à écart nul sur chaque site | B37: =IF(AND('Reprise des données'!H17="Oui",'Reprise des données'!H18="Oui",'Reprise des données'!H19="Oui"),"OK","À faire") | C37: Magasin, boutique pilote, seconde boutique : voir le tableau de rapprochement de l'onglet « Reprise des données ».
A38: Scénarios RV1-01 à RV1-07 joués sans écart | B38: =IF(AND(COUNTIF('Recette Lot 1'!$G$5:$G$200,"Échec")=0,COUNTIF('Recette Lot 1'!$G$5:$G$200,"Bloqué")=0,COUNTIF('Recette Lot 1'!$G$5:$G$200,"À faire")=0),"OK","À faire") | C38: Chaque étape de chaque scénario doit être renseignée « Réussi ».
A39: Données de reprise validées par leurs responsables | B39: =IF(COUNTIF('Reprise des données'!$G$5:$G$10,"Validé")=ROWS('Reprise des données'!$G$5:$G$10),"OK","À faire") | C39: Onglet « Reprise des données », colonne Statut.
A40: Tests automatiques au vert | B40: À faire | C40: À confirmer avant la recette : exécuter la suite complète (mvn test) sur la version déployée.
A42: 5. Limites connues du lot (cas « Partiel » ou « À livrer »)
A43: Fonction | B43: Réf. SRS | C43: Situation dans ce lot
A44: Photo des motos endommagées et pièces jointes | B44: US-027, US-042, EF-TRF-06 | C44: Le module Documents (pièces, photos, archivage du bon signé) arrive au sprint S10. Dans ce lot : motif texte et référence de pièce.
A45: Scan par appareil photo (caméra) | B45: US-024, EF-REC-10 | C45: Saisie au clavier et lecteur de codes-barres externe livrés ; la lecture par caméra est à ajouter.
A46: Stock à une date passée | B46: US-046, EF-STK-08 | C46: Le journal des mouvements est complet et en ajout seul ; l'écran de reconstitution arrive avec les rapports.
A47: Contrôle nocturne de cohérence et alerte de seuil de stock | B47: EF-STK-09, EF-STK-11 | C47: Les contraintes de base empêchent les incohérences ; la détection et l'alerte arrivent avec le module Anomalies.
A48: Inversion d'une réception validée | B48: EF-REC-09 | C48: À venir avec les ajustements ; en attendant, aucune annulation d'une réception validée n'est possible (RG-18).
A49: Correction de numéro refusée si facturé | B49: US-013 | C49: Point d'extension prêt côté châssis ; la règle s'active avec la facturation (lot 2).
A50: Prix conservés par les commandes validées | B50: US-011 | C50: L'historique des prix est livré ; le raccordement aux commandes clients arrive avec elles.
A51: Envoi réel des e-mails | B51: EF-NOT-02, EF-ADM-01 | C51: Le serveur SMTP du compte d'hébergement refuse l'envoi sortant (554 5.7.1) : problème de compte à régler par l'hébergeur. L'application ne plante pas, les notifications internes fonctionnent.
A52: Import en masse des modèles et prix | B52: SRS 14.2 | C52: Les modèles se saisissent à l'écran ; l'import Excel du catalogue n'est pas livré.
A53: Écran du journal d'audit | B53: US-154, AUD | C53: Le journal est écrit, chaîné et protégé en base ; l'activité récente est visible au tableau de bord Administration. L'écran de consultation complet arrive au sprint S11.
A54: Traitement des anomalies | B54: EF-ANO | C54: L'anomalie A12 est ouverte automatiquement ; la justification, la régularisation et la clôture viennent avec le module Anomalies (S10).
A56: 6. Environnement et organisation de la recette
A57: Environnement : instance de recette dédiée (application, base PostgreSQL 16, serveur de messagerie de test), distincte de l'environnement de développement. Données de test à créer à partir de l'onglet « Comptes de test » et du jeu de l'onglet « Jeu de données import ».
A58: Version à recetter : à consigner ici avant le premier test (branche, numéro de migration — V14 attendue —, date de déploiement) : ____________________
A59: Déroulement conseillé : 1) ADM et CAT ; 2) APP ; 3) REC ; 4) STK ; 5) TRF ; 6) reprise du stock (import puis pointage) ; 7) scénarios de recette RV1-01 à RV1-07 ; 8) transverse (droits, performance, navigateurs).
A60: Règle : un cas qui échoue donne lieu à une anomalie (onglet « Anomalies ») ; le cas est rejoué après correction et le résultat mis à jour. Les cas de profil « Compte des deux sites », de séparation des tâches ou de délai exigent la collaboration de deux testeurs.
A61: Les tests automatiques de l'équipe (onglet « Tests automatiques ») couvrent déjà les règles de gestion et les droits par appel direct à l'API ; la recette manuelle vérifie les parcours, l'ergonomie et la conformité au métier.

Sheet Plan de test
A1: Plan de test — Jalon V1 · Lot 1 « Stock et logistique »
A2: Un cas par ligne. Remplir les colonnes Résultat, Date, Testeur, N° anomalie et Commentaire. Les listes déroulantes sont dans les colonnes Résultat et Prio.
A3: Légende : Prio. M = Doit, S = Devrait, C = Pourrait (SRS 1.3). Couverture développement : Livré / Partiel (voir commentaire et onglet Synthèse) / À livrer (cas à rejouer plus tard).
A4: N° | B4: Module | C4: Référence (story / exigence) | D4: Cas de test | E4: Profil testeur | F4: Pré-requis | G4: Étapes | H4: Résultat attendu | I4: Type | J4: Prio. | K4: Couverture développement | L4: Test automatique | M4: Résultat | N4: Date | O4: Testeur | P4: N° anomalie | Q4: Commentaire / preuve
A5: TC-ADM-001 | B5: ADM Administration | C5: US-001, EF-ADM-02 | D5: Créer un utilisateur avec ses rôles et ses emplacements | E5: Administrateur | F5: Un magasin et une boutique existent. Un rôle « magasin » existe. | G5: 1. Utilisateurs > Nouvel utilisateur. 2. Saisir nom, prénom, e-mail, rôle « Magasin », emplacement « Magasin de Cotonou ». 3. Enregistrer. 4. Ouvrir le lien d'activation reçu, choisir un mot de passe conforme. 5. Se connecter avec le nouveau compte. | H5: Le compte est créé « En attente d'activation » et passe « Actif » après activation. L'utilisateur voit ses rôles et son seul emplacement sur l'accueil. La création figure au journal d'audit (auteur, date, valeurs). | I5: Fonctionnel | J5: M | K5: Livré | L5: AuthEtUtilisateursTest | M5: À tester
A6: TC-ADM-002 | B6: ADM Administration | C6: US-001, EF-ADM-13 | D6: Périmètre : un utilisateur ne voit que ses emplacements | E6: Magasinier (Cotonou) | F6: Un second magasin et un châssis disponible dans chacun. | G6: 1. Se connecter en magasinier de Cotonou. 2. Stock > Stock : consulter la synthèse. 3. Tenter d'ouvrir par l'adresse la fiche d'un châssis de l'autre magasin. 4. Idem pour une réception et un transfert de l'autre magasin. | H6: Seul le stock de Cotonou apparaît. La fiche, la réception et le transfert de l'autre magasin répondent « introuvable » (404), sans révéler leur existence. | I6: Droits et périmètre | J6: M | K6: Livré | L6: StockTest, ChassisTest, ReceptionsTest, TransfertsTest | M6: À tester
A7: TC-ADM-003 | B7: ADM Administration | C7: US-001 | D7: Lien d'activation expiré ou déjà utilisé | E7: Administrateur | F7: Un utilisateur en attente d'activation. | G7: 1. Utiliser le lien d'activation une première fois. 2. Réutiliser le même lien. 3. Pour un lien expiré : Utilisateurs > Renvoyer l'activation, puis utiliser l'ancien lien. | H7: Le second usage est refusé avec un message clair. L'ancien lien est invalidé par le nouveau. Le renvoi est tracé au journal. | I7: Fonctionnel | J7: M | K7: Livré | L7: AuthEtUtilisateursTest | M7: À tester
A8: TC-ADM-004 | B8: ADM Administration | C8: US-002, EF-ADM-10 | D8: Verrouillage du compte après cinq échecs de connexion | E8: Tout profil | F8: Un compte actif de test (sans second facteur). | G8: 1. Saisir 5 fois un mauvais mot de passe. 2. Saisir ensuite le bon mot de passe. 3. En administrateur, constater l'état du compte puis le déverrouiller. | H8: Après le 5e échec le compte est verrouillé (message identique à un échec simple, sans indice). Le bon mot de passe est refusé tant que le compte est verrouillé. Les échecs et le verrouillage figurent au journal de sécurité. | I8: Fonctionnel | J8: M | K8: Livré | L8: AuthEtUtilisateursTest | M8: À tester
A9: TC-ADM-005 | B9: ADM Administration | C9: US-002, EF-ADM-10 | D9: Second facteur obligatoire pour Administrateur, Direction et Comptabilité | E9: Direction | F9: Un compte Direction sans second facteur activé ; une application d'authentification sur téléphone. | G9: 1. Se connecter avec e-mail et mot de passe. 2. Scanner le QR code (ou saisir la clé) puis saisir le code à 6 chiffres. 3. Noter les codes de secours affichés. 4. Se déconnecter puis se reconnecter : saisir le code TOTP. 5. Tenter un code erroné, puis un code de secours (une seule fois). | H9: Sans enrôlement, l'accès est impossible. Le code correct ouvre la session, le code erroné est refusé, un code de secours ne marche qu'une fois. Les secrets sont stockés chiffrés. | I9: Fonctionnel | J9: M | K9: Livré | L9: DoubleAuthentificationTest, TotpTest | M9: À tester
A10: TC-ADM-006 | B10: ADM Administration | C10: US-002 | D10: Réinitialisation du mot de passe | E10: Tout profil | F10: Un compte actif. | G10: 1. « Mot de passe oublié » : saisir l'e-mail. 2. Utiliser le lien reçu pour définir un nouveau mot de passe. 3. Se reconnecter avec l'ancien, puis le nouveau. 4. Demander la réinitialisation d'une adresse inconnue. | H10: L'ancien mot de passe est refusé, le nouveau accepté. L'adresse inconnue reçoit la même réponse neutre. Les sessions ouvertes sont fermées. | I10: Fonctionnel | J10: M | K10: Livré | L10: AuthEtUtilisateursTest | M10: À tester
A11: TC-ADM-007 | B11: ADM Administration | C11: US-003, EF-ADM-03 | D11: Régler les permissions d'un rôle action par action | E11: Administrateur | F11: Un rôle personnalisé et un utilisateur qui le porte, connecté. | G11: 1. Utilisateurs > Rôles : retirer une permission du rôle (par exemple « Transferts : valider »). 2. Enregistrer. 3. Côté utilisateur : constater la fermeture de session, se reconnecter. 4. Tenter l'action retirée par l'écran, puis par un appel direct à l'API (outil de test HTTP). | H11: Le bouton disparaît, l'appel direct à l'API répond 403. La modification est tracée avec les droits avant et après. La Direction est notifiée (cf. TC-ADM-015). | I11: Droits et périmètre | J11: M | K11: Livré | L11: RolesEtPermissionsTest | M11: À tester
A12: TC-ADM-008 | B12: ADM Administration | C12: EF-ADM-03, SRS 9.1 | D12: Matrice de départ des rôles conforme au SRS | E12: Administrateur | F12: Base neuve (rôles livrés par défaut). | G12: 1. Ouvrir chaque rôle livré (Administrateur, Direction, Responsable commercial, Commercial, Comptabilité/Caisse, Magasin, Contrôleur, Boutique). 2. Comparer ses permissions à la matrice de la section 9.1 du SRS (L, C, V, CV, T). | H12: Chaque rôle porte exactement les droits de la matrice. Les permissions spéciales (prix d'achat, stock modifier, stock bloquer, importer le stock initial, retour arrière commande…) sont attribuées aux rôles prévus. | I12: Droits et périmètre | J12: M | K12: Livré | L12: RolesEtPermissionsTest | M12: À tester
A13: TC-ADM-009 | B13: ADM Administration | C13: US-004, EF-ADM-08 | D13: Créer magasins et boutiques, fixer le mode de chaque boutique | E13: Administrateur | F13: Un magasin existe. | G13: 1. Emplacements > Nouveau : créer une boutique en mode A. 2. Créer une boutique en mode B sans magasin de rattachement. 3. Créer une boutique en mode B avec rattachement. 4. Vérifier que l'emplacement de transit interne existe et n'est pas modifiable. | H13: Le mode A est accepté. Le mode B sans rattachement est refusé. Le transit interne est géré par le système (ni modifiable, ni désactivable). | I13: Fonctionnel | J13: M | K13: Livré | L13: EmplacementsTest | M13: À tester
A14: TC-ADM-010 | B14: ADM Administration | C14: US-004, EF-ADM-08, EF-ADM-09 | D14: Changement de mode et désactivation refusés s'il reste du stock | E14: Administrateur | F14: Une boutique avec au moins une moto disponible. | G14: 1. Tenter de passer la boutique du mode A au mode B. 2. Tenter de la désactiver. 3. Faire livrer ou transférer toutes ses motos, puis recommencer. | H14: Avec du stock (ou un transfert/une réception en cours), les deux opérations sont refusées avec un motif. Sans stock, elles passent. | I14: Règle de gestion | J14: M | K14: Livré | L14: EmplacementsTest, StockTest | M14: À tester
A15: TC-ADM-011 | B15: ADM Administration | C15: US-005, EF-ADM-05, EF-ADM-06 | D15: Paramétrer seuils et délais de contrôle avec date d'effet | E15: Administrateur | F15: Aucun paramètre fiscal ni de contrôle renseigné. | G15: 1. Paramètres > Paramètres de contrôle : renseigner « Délai de réception d'un transfert » = 5 jours, date d'effet aujourd'hui. 2. Programmer une autre valeur à une date future. 3. Consulter l'historique du paramètre. 4. Saisir une valeur hors bornes ou non numérique. | H15: La valeur s'applique aux contrôles suivants. La future valeur n'est pas appliquée avant sa date. L'historique conserve ancienne et nouvelle valeur, auteur et date. Les valeurs invalides sont refusées. Tant qu'un seuil n'est pas fixé, le contrôle correspondant n'est pas appliqué. | I15: Fonctionnel | J15: M | K15: Livré | L15: ReferentielsEtParametresTest | M15: À tester
A16: TC-ADM-012 | B16: ADM Administration | C16: EF-REC-05, EF-TRF-05, RG-19 | D16: Paramètres de séparation des tâches (Oui par défaut) | E16: Administrateur | F16: Paramètres de contrôle affichés. | G16: 1. Vérifier « Réception validée par un autre utilisateur » et « Transfert réceptionné par un autre utilisateur » : valeur par défaut Oui, sans « À renseigner ». 2. Passer l'un à Non, rejouer TC-REC-006 ou TC-TRF-005, puis remettre Oui. | H16: Le défaut est Oui et ne compte pas dans l'avancement du paramétrage. À Non, la même personne peut valider ; la modification est historisée. | I16: Règle de gestion | J16: M | K16: Livré | L16: ReceptionsTest, TransfertsTest | M16: À tester
... A22: TC-ADM-018 | B22: ADM Administration | C22: TDB, EF-STK-10 | D22: Tableaux de bord par domaine et droits d'accès | E22: Direction, Magasinier, Commercial, Administrateur | F22: Un compte par profil. | G22: 1. Se connecter successivement avec chaque profil. 2. Observer le menu « Tableau de bord » et la page d'arrivée. 3. Tenter d'ouvrir par l'adresse un tableau de bord non autorisé et l'API correspondante. | H22: Management, Commercial et Administration sont trois pages séparées, chacune visible selon son droit. Un droit absent renvoie à une page autorisée (ou à l'accueil) et l'API répond 403. Les chiffres suivent le périmètre de la personne. | I22: Droits et périmètre | J22: M | K22: Livré | L22: TableauDeBordMetierTest, ReferentielsEtParametresTest | M22: À tester
A23: TC-ADM-019 | B23: ADM Administration | C23: SRS 14.5 | D23: Menu filtré par permissions | E23: Boutique, Magasin, Direction | F23: Comptes de chaque profil. | G23: 1. Comparer les entrées de menu affichées pour chaque profil. | H23: Un groupe de menu disparaît quand aucune de ses entrées n'est accessible. Aucune entrée ne mène à un écran interdit. | I23: Droits et périmètre | J23: S | K23: Livré | M23: À tester
A24: TC-ADM-020 | B24: ADM Administration | C24: AUD-01 à AUD-03, US-155 | D24: Journal d'audit en ajout seul | E24: Administrateur, équipe technique | F24: Plusieurs opérations déjà effectuées (réception validée, transfert expédié, blocage de châssis, import). | G24: 1. Tableau de bord Administration > Activité récente : lire les dernières actions. 2. En base (table journal_audit), retrouver l'opération : action, auteur, date, valeurs avant/après, motif. 3. En base, tenter un UPDATE puis un DELETE sur le journal, sur les mouvements de stock et sur l'historique des prix. 4. Vérifier la continuité du chaînage de hachage. | H24: Chaque ligne porte auteur, date, action, objet, valeurs avant/après et motif. Les écritures de modification ou de suppression sont refusées par la base (déclencheur). Le chaînage reste intact. L'écran complet du journal d'audit n'est pas livré dans ce lot (voir limites). | I24: Audit et traçabilité | J24: M | K24: Partiel | L24: JournalAuditTest | M24: À tester
A25: TC-ADM-021 | B25: ADM Administration | C25: EF-ADM-11, SRS 10.9 | D25: Session : persistance, déconnexion, suspension et changement de rôle | E25: Administrateur et utilisateur de test | F25: Un compte actif connecté dans un navigateur. | G25: 1. Naviguer entre plusieurs écrans : la connexion persiste. 2. Se déconnecter : la session et l'accès à l'API sont fermés. 3. En administrateur : suspendre le compte connecté. 4. Reconnecter le compte, puis changer ses rôles par l'administrateur. 5. Revenir sur le navigateur du compte. | H25: L'état de connexion survit aux requêtes et prend fin à la déconnexion. Une suspension ou un changement de rôle ferme la session immédiatement pour que les droits s'appliquent à la prochaine connexion. Une écriture sans jeton CSRF est refusée. | I25: Fonctionnel | J25: S | K25: Livré | L25: AuthEtUtilisateursTest, SecuriteTest | M25: À tester
A26: TC-CAT-001 | B26: CAT Catalogue et châssis | C26: US-010, EF-CAT-01 | D26: Créer un modèle avec ses prix | E26: Responsable commercial | F26: Aucun modèle de code CG125-2026. | G26: 1. Catalogue > Modèles > Nouveau. 2. Saisir marque, modèle, code article CG125-2026, format de châssis (expression), prix de vente 1 250 000, prix minimum 1 150 000. 3. Enregistrer. 4. Tenter de créer un second modèle avec le même code (casse différente). 5. Tenter un prix minimum supérieur au prix de vente. | H26: Le modèle est créé avec son prix à la date du jour. Le code article est unique sans tenir compte de la casse. Le prix minimum ne peut dépasser le prix de vente. | I26: Fonctionnel | J26: M | K26: Livré | L26: CatalogueTest | M26: À tester
A27: TC-CAT-002 | B27: CAT Catalogue et châssis | C27: US-011, EF-CAT-02 | D27: Changer un prix avec une date d'effet et consulter l'historique | E27: Responsable commercial | F27: Un modèle existant avec un prix de vente. | G27: 1. Fiche modèle > Changer le prix : nouveau prix, date d'effet dans 10 jours, motif. 2. Constater que le prix en vigueur est inchangé et que le prix est « programmé ». 3. Consulter l'historique des prix. 4. Tenter de saisir une date d'effet passée. | H27: Le prix programmé s'applique à sa date. L'historique (ajout seul) conserve chaque valeur, date d'effet, auteur et motif. Une date passée est refusée. | I27: Fonctionnel | J27: M | K27: Livré | L27: CatalogueTest | M27: À tester
A28: TC-CAT-003 | B28: CAT Catalogue et châssis | C28: US-011, EF-CAT-03 | D28: Baisser le prix minimum exige la validation catalogue | E28: Commercial / Responsable commercial | F28: Un modèle ; un compte avec « catalogue : modifier » mais sans « catalogue : valider ». | G28: 1. Sans le droit valider : baisser le prix minimum. 2. Avec le droit valider (Direction) : baisser le prix minimum. 3. Vérifier que min ≤ vente sur toute la chronologie (y compris prix programmés). | H28: Sans le droit, la baisse est refusée. Avec le droit, elle passe et est tracée. L'invariant minimum ≤ vente tient sur l'ensemble des prix passés et futurs. | I28: Règle de gestion | J28: M | K28: Livré | L28: CatalogueTest | M28: À tester
A29: TC-CAT-004 | B29: CAT Catalogue et châssis | C29: US-011 | D29: Les commandes déjà validées gardent leur prix | E29: Commercial | F29: Module des commandes clients (lot 2). | G29: 1. Valider une commande à un prix. 2. Changer le prix du modèle. 3. Rouvrir la commande. | H29: La commande conserve le prix validé. À rejouer à la recette du lot 2 : l'historique des prix est livré, le raccordement aux commandes arrive avec elles. | I29: Règle de gestion | J29: M | K29: À livrer | M29: Non livré
A30: TC-CAT-005 | B30: CAT Catalogue et châssis | C30: EF-CAT-08, SRS 9.2 | D30: Visibilité des prix d'achat selon permission | E30: Acheteur, Commercial | F30: Un modèle avec un prix d'achat de référence. | G30: 1. En commercial (sans « prix d'achat : voir ») ouvrir la fiche modèle et la liste des châssis. 2. En acheteur/Direction, refaire. 3. Interroger l'API de détail modèle avec chaque compte. | H30: Sans le droit, prix d'achat et coût de revient sont absents des écrans, des exports et des réponses API (champ masqué, pas seulement caché). Avec le droit ils apparaissent. | I30: Droits et périmètre | J30: M | K30: Livré | L30: CatalogueTest, ChassisTest | M30: À tester
A31: TC-CAT-006 | B31: CAT Catalogue et châssis | C31: US-012, EF-CAT-05 | D31: Fiche châssis : toute l'histoire d'une moto | E31: Magasinier, Direction | F31: Une moto passée par colisage, réception, transfert et un blocage. | G31: 1. Stock > Châssis (ou Catalogue > Châssis) : rechercher le numéro. 2. Ouvrir la fiche. 3. Lire la chronologie. 4. Se connecter en magasinier sans « prix d'achat : voir » et vérifier le coût. | H31: La fiche affiche statut, emplacement, date d'entrée, ancienneté et chaque événement daté avec son auteur et ses statuts avant/après (création, arrivée, réception, expédition, réception de transfert, blocage…). Le coût est masqué sans la permission. | I31: Fonctionnel | J31: M | K31: Livré | L31: ChassisTest | M31: À tester
A32: TC-CAT-007 | B32: CAT Catalogue et châssis | C32: US-013, EF-CAT-07 | D32: Corriger un numéro de châssis avec validation d'un collègue | E32: Responsable magasin (demandeur), Magasinier 2 (valideur) | F32: Un châssis au numéro mal saisi. | G32: 1. Fiche châssis > Corriger avec autorisation : nouveau numéro et motif. 2. Constater la demande « en attente ». 3. Tenter de la valider avec le même utilisateur. 4. La valider avec un second utilisateur. 5. Rechercher l'ancien numéro. | H32: Le demandeur ne peut pas valider sa propre demande. Après validation le châssis porte le nouveau numéro, l'ancien reste trouvable et affiché sur la fiche. Un refus exige un motif. Tout est au journal. | I32: Règle de gestion | J32: M | K32: Livré | L32: ChassisTest | M32: À tester
A33: TC-CAT-008 | B33: CAT Catalogue et châssis | C33: US-013 | D33: Correction refusée si le châssis figure sur une facture normalisée | E33: Responsable magasin | F33: Module de facturation (lot 2). | G33: 1. Facturer un châssis (facture normalisée). 2. Demander la correction de son numéro. | H33: La demande est refusée. Le point d'extension existe côté châssis ; la règle s'active avec le module de facturation (lot 2). | I33: Règle de gestion | J33: M | K33: À livrer | M33: Non livré
A34: TC-CAT-009 | B34: CAT Catalogue et châssis | C34: EF-CAT-04, EF-CAT-06 | D34: Liste des châssis : recherche, filtres, export | E34: Direction, Magasinier | F34: Une centaine de châssis de statuts variés. | G34: 1. Filtrer par statut, modèle, emplacement, ancienneté minimale (30/60/90/180 jours). 2. Rechercher par fragment de numéro, de moteur, ou par ancien numéro corrigé. 3. Exporter la liste filtrée (CSV) avec puis sans le droit d'export. | H34: Les filtres se combinent et se retrouvent dans l'adresse (liens depuis le stock). L'export respecte le périmètre et les colonnes autorisées, et est tracé au journal. Sans le droit : refusé. | I34: Fonctionnel | J34: S | K34: Livré | L34: ChassisTest | M34: À tester
A35: TC-CAT-010 | B35: CAT Catalogue et châssis | C35: RG-01, EF-CAT-04 | D35: Unicité du numéro de châssis (casse, tirets, espaces ignorés) | E35: Magasinier | F35: Un châssis LWBAB12CD34EF56GH en stock. | G35: 1. Tenter de le recréer via la réception avec la saisie « lwb-ab12 cd34-ef56gh ». 2. Tenter de l'importer dans un fichier de stock initial. 3. Tenter de le scanner comme moto non annoncée. | H35: Chaque tentative est refusée comme doublon avec l'emplacement actuel de la moto. Un seul châssis existe par numéro normalisé (index unique en base). | I35: Règle de gestion | J35: M | K35: Livré | L35: ChassisTest, ReceptionsTest, StockInitialTest | M35: À tester
A36: TC-APP-001 | B36: APP Approvisionnements | C36: US-020, EF-APP-01 | D36: Créer une commande fournisseur | E36: Acheteur | F36: Un fournisseur actif et un modèle avec prix d'achat. | G36: 1. Approvisionnements > Commandes > Nouvelle. 2. Fournisseur, devise USD, taux de change 600, incoterm FOB, base de prix FOB, lignes : modèle A × 3 à 1 000 USD, modèle B × 2 à 800 USD. 3. Enregistrer. 4. Consulter le stock avant/après. | H36: La commande est créée au statut COMMANDÉE avec son numéro PO-. Le stock ne change pas (RG-06). Le total est calculé en devise et en FCFA. La Direction est notifiée. La commande est au journal. | I36: Fonctionnel | J36: M | K36: Livré | L36: CommandesFournisseurTest | M36: À tester
A37: TC-APP-002 | B37: APP Approvisionnements | C37: US-021, EF-APP-02 | D37: Faire avancer la commande d'étape en étape | E37: Acheteur | F37: Une commande COMMANDÉE. | G37: 1. Avancer vers CONFIRMÉE (référence proforma). 2. Tenter de passer directement à AU PORT. 3. Avancer étape par étape jusqu'à la fin permise. 4. Consulter l'historique de la commande. | H37: Chaque étape enregistre date et auteur. Une étape sautée est refusée. Les étapes « Réception partielle » et « Réceptionnée » ne s'avancent jamais à la main. | I37: Règle de gestion | J37: M | K37: Livré | L37: CommandesFournisseurTest | M37: À tester
A38: TC-APP-003 | B38: APP Approvisionnements | C38: EF-APP-02, EF-APP-04 | D38: Étapes de la commande conditionnées par l'arrivage | E38: Acheteur | F38: Une commande confirmée avec un arrivage. | G38: 1. Tenter « Dédouanement » alors qu'aucun dédouanement n'est démarré. 2. Tenter « Au port » sans date d'arrivée réelle. 3. Saisir la date d'arrivée, démarrer puis terminer le dédouanement de l'arrivage. 4. Avancer la commande à « À réceptionner ». | H38: Chaque passage est refusé tant que la condition n'est pas remplie, avec un message qui dit laquelle. Quand le dédouanement est terminé, les motos annoncées passent « À réceptionner » et le magasin est notifié. | I38: Règle de gestion | J38: M | K38: Livré | L38: ArrivagesTest, CommandesFournisseurTest | M38: À tester
A39: TC-APP-004 | B39: APP Approvisionnements | C39: US-020, SRS 9.3 | D39: Retour arrière de statut : droit spécifique | E39: Acheteur, Direction | F39: Une commande à une étape avancée. | G39: 1. En acheteur : tenter un retour arrière. 2. En Direction (droit « retour arrière ») : faire un retour arrière avec motif. | H39: Refusé sans le droit. Avec le droit, motif obligatoire, historisé. | I39: Droits et périmètre | J39: S | K39: Livré | L39: CommandesFournisseurTest | M39: À tester
A40: TC-APP-005 | B40: APP Approvisionnements | C40: US-022, EF-APP-03 | D40: Saisir les frais d'un arrivage avec leurs pièces | E40: Acheteur | F40: Un arrivage rattaché à une commande. | G40: 1. Arrivage > Frais > Ajouter : type Fret, 1 200 USD, taux 600, sans pièce. 2. Ajouter un frais en FCFA avec pièce. 3. Annuler un frais avec motif. 4. Consulter le coût provisoire de la commande. | H40: Le montant FCFA est arrondi selon la règle et recalculé. Le frais sans pièce est signalé (alerte). L'annulation exige un motif et reste visible. Le coût de revient provisoire par moto est recalculé. | I40: Fonctionnel | J40: M | K40: Livré | L40: ArrivagesTest | M40: À tester
A41: TC-APP-006 | B41: APP Approvisionnements | C41: US-023, EF-APP-06 | D41: Importer la liste de colisage (CSV et Excel) | E41: Acheteur | F41: Un arrivage et deux fichiers : un CSV et un XLSX de colisage (10 lignes dont 2 fautives : un doublon, un code article inconnu). | G41: 1. Arrivage > Colisage : charger le fichier en mode simulation. 2. Lire le rapport. 3. Relancer sans simulation. 4. Recharger le même fichier. | H41: La simulation ne crée rien. L'import crée les châssis « En transit fournisseur » (hors stock) avec leur arrivage ; les lignes fautives sont rejetées avec numéro de ligne et motif. Le second import ne crée aucun doublon. La quantité cumulée ne peut dépasser la commande. | I41: Fonctionnel | J41: S | K41: Livré | L41: ArrivagesTest | M41: À tester
A42: TC-APP-007 | B42: APP Approvisionnements | C42: EF-APP-09 | D42: Suivi des arrivages : retard, état dérivé | E42: Acheteur, Direction | F42: Un arrivage avec date d'arrivée prévue dépassée et non arrivé. | G42: 1. Approvisionnements > Arrivages en cours. 2. Constater l'état et le retard en jours. 3. Saisir la date d'arrivée réelle. | H42: L'état est calculé (en transit, au port, dédouanement, à réceptionner) et le retard s'affiche tant que la marchandise n'est pas arrivée. Le tableau de bord Management le reprend. | I42: Fonctionnel | J42: S | K42: Livré | L42: ArrivagesTest, TableauDeBordMetierTest | M42: À tester
A43: TC-APP-008 | B43: APP Approvisionnements | C43: SRS 9.2 | D43: Droits du module : acheteur, magasin, contrôleur | E43: Magasinier, Contrôleur | F43: Une commande existante. | G43: 1. En magasinier : ouvrir les commandes. 2. Tenter de créer une commande et de voir les prix d'achat. | H43: Lecture seule pour le magasin et le contrôleur. La création est refusée côté API. Les prix sont masqués sans « prix d'achat : voir » (ou « approvisionnements : créer » pour les prix de commande). | I43: Droits et périmètre | J43: M | K43: Livré | L43: CommandesFournisseurTest | M43: À tester
A44: TC-REC-001 | B44: REC Réceptions | C44: EF-REC-01 | D44: Ouvrir une réception depuis un arrivage dédouané | E44: Magasinier | F44: Une commande « À réceptionner », un arrivage dédouané avec colisage, un magasin dans le périmètre. | G44: 1. Stock > Réceptions : l'arrivage apparaît dans « Arrivages à réceptionner ». 2. Cliquer Réceptionner. 3. Retourner à la liste et recliquer sur le même arrivage. 4. Tenter d'ouvrir une réception sur un arrivage non dédouané. | H44: Une réception BROUILLON est créée avec son numéro. Une seule réception ouverte par arrivage (le bouton devient « Reprendre »). Un arrivage non dédouané est refusé. Le lieu de réception est un magasin actif du périmètre. | I44: Fonctionnel | J44: M | K44: Livré | L44: ReceptionsTest | M44: À tester
A45: TC-REC-002 | B45: REC Réceptions | C45: US-024, EF-REC-02, EF-REC-03 | D45: Scanner les châssis reçus : contrôles à la saisie | E45: Magasinier | F45: Une réception ouverte pour un colisage de 3 motos modèle A et 1 moto modèle B. | G45: 1. Scanner un châssis annoncé (saisie en minuscules avec tirets). 2. Rescanner le même. 3. Scanner un numéro au mauvais format du modèle. 4. Scanner un châssis déjà en stock ailleurs. 5. Scanner un châssis d'un autre modèle que celui annoncé. 6. Scanner 20 numéros d'affilée très vite (lecteur). | H45: Chaque contrôle affiche son message (doublon, format, déjà en stock, modèle différent). Aucun scan n'est perdu lors d'une saisie rapide. Le compteur attendu / reçu / écart par modèle suit en continu. | I45: Fonctionnel | J45: M | K45: Livré | L45: ReceptionsTest | M45: À tester
... A51: TC-REC-008 | B51: REC Réceptions | C51: EF-REC-08 | D51: Procès-verbal de réception en PDF | E51: Responsable magasin | F51: Une réception validée avec écarts. | G51: 1. Ouvrir la réception validée > Télécharger le procès-verbal. 2. Vérifier le contenu. 3. Tenter de l'obtenir pour une réception encore en brouillon. | H51: Le PDF contient magasin, arrivage, commande, rapprochement attendu/reçu/écart par modèle, liste des châssis (état, observation), manquants, observations et cases de signature. Indisponible tant que la réception n'est pas validée. | I51: Fonctionnel | J51: M | K51: Livré | L51: ReceptionsTest | M51: À tester
A52: TC-REC-009 | B52: REC Réceptions | C52: EF-REC-10 | D52: Saisie sur téléphone ou tablette, appareil photo comme lecteur | E52: Magasinier | F52: Un smartphone ou une tablette sur le réseau de recette. | G52: 1. Ouvrir l'écran de réception sur le téléphone. 2. Saisir et valider des numéros au clavier, puis avec un lecteur Bluetooth. 3. Essayer de scanner un code-barres avec la caméra. | H52: L'écran est utilisable au doigt (champ large, retour clavier). Le scan par caméra n'est pas livré dans ce lot : le clavier et le lecteur externe fonctionnent. | I52: Fonctionnel | J52: M | K52: Partiel | M52: À tester
A53: TC-REC-010 | B53: REC Réceptions | C53: EF-REC-09 | D53: Corriger une réception validée par inversion | E53: Responsable magasin avec droit spécifique | F53: Une réception validée dont les châssis sont encore disponibles. | G53: 1. Tenter d'inverser la réception. | H53: Non livré dans ce lot (inversion à venir avec le module des ajustements) : aucun bouton d'annulation d'une réception validée n'existe, ce qui respecte RG-18 en attendant. | I53: Règle de gestion | J53: M | K53: À livrer | M53: Non livré
A54: TC-REC-011 | B54: REC Réceptions | C54: SRS 9.2, EF-ADM-13 | D54: Droits et périmètre du module réceptions | E54: Magasinier, Boutique, Commercial | F54: Une réception dans le magasin A. | G54: 1. En magasinier du magasin B : ouvrir la réception du magasin A. 2. En boutique ou commercial : ouvrir le module et tenter une création par l'API. | H54: La réception d'un autre magasin est introuvable. Boutique et commercial n'ont pas accès au module (403). | I54: Droits et périmètre | J54: M | K54: Livré | L54: ReceptionsTest | M54: À tester
A55: TC-STK-001 | B55: STK Stock | C55: US-040, EF-STK-01, EF-STK-03 | D55: Voir le stock physique, réservé, disponible, bloqué et en transit par modèle | E55: Magasinier | F55: Dans un magasin : 5 disponibles, 2 réservées, 1 en préparation, 1 bloquée, 1 livrée. (Reproduire un cas 100 / 20 / 80 par import si possible.) | G55: 1. Stock > Stock. 2. Lire les compteurs du magasin et la ligne du modèle. 3. Cliquer « Voir les châssis ». | H55: Physique 9, réservé 3, bloqué 1, disponible 5 (= physique − réservé − bloqué). La livrée n'est pas comptée. Avec 100 motos physiques dont 20 réservées l'écran affiche 80 disponibles. Le lien ouvre la liste des châssis déjà filtrée. | I55: Fonctionnel | J55: M | K55: Livré | L55: StockTest | M55: À tester
A56: TC-STK-002 | B56: STK Stock | C56: US-041, EF-STK-02 | D56: Stock global consolidé sans double comptage | E56: Direction | F56: Magasin, boutique, un dépôt revendeur, une moto en transit interne, deux motos « en transit fournisseur ». | G56: 1. En Direction : Stock > Stock (vue consolidée). 2. Comparer le total aux lignes par emplacement. 3. Vérifier la carte « En cours d'importation ». | H56: Stock global = sites + transit interne + dépôt-vente, chaque châssis compté une fois. Le total égale la somme des emplacements. Les motos non encore reçues sont affichées à part, hors stock. | I56: Règle de gestion | J56: M | K56: Livré | L56: StockTest | M56: À tester
A57: TC-STK-003 | B57: STK Stock | C57: EF-STK-10 | D57: Stock limité aux emplacements de l'utilisateur | E57: Boutique, Magasinier | F57: Du stock dans plusieurs emplacements. | G57: 1. En boutique : Stock > Stock, Mouvements, Châssis bloqués, Transferts. 2. Appeler l'API de stock d'un autre emplacement. | H57: Seuls les emplacements de la personne apparaissent. Les emplacements hors périmètre sont introuvables (404) et le stock global n'est pas exposé. | I57: Droits et périmètre | J57: M | K57: Livré | L57: StockTest | M57: À tester
A58: TC-STK-004 | B58: STK Stock | C58: US-042, EF-STK-06 | D58: Bloquer un châssis en litige (motif et pièce obligatoires) puis le débloquer | E58: Responsable magasin | F58: Un châssis disponible, un autre réservé. | G58: 1. Fiche châssis > Bloquer sans motif, puis sans pièce. 2. Bloquer avec motif et référence de pièce. 3. Tenter de bloquer le châssis réservé. 4. Stock > Châssis bloqués : lire le motif et l'ancienneté. 5. Débloquer avec un motif. 6. Lire l'historique du châssis. | H58: Motif et pièce sont obligatoires. Seule une moto disponible se bloque. Le châssis bloqué n'est plus proposé à la vente (disponible − 1, physique inchangé). Le déblocage exige un motif. Blocage et déblocage sont tracés (mouvement, audit) et le contrôle est notifié. | I58: Fonctionnel | J58: M | K58: Livré | L58: StockTest | M58: À tester
A59: TC-STK-005 | B59: STK Stock | C59: US-042 | D59: Pièce justificative jointe au blocage | E59: Responsable magasin | F59: Module Documents (lot ultérieur). | G59: 1. Bloquer un châssis en joignant un fichier ou une photo. | H59: Dans ce lot la pièce est une référence texte (n° de PV, de litige). Le dépôt de fichier arrive avec le module Documents. | I59: Fonctionnel | J59: M | K59: Partiel | L59: StockTest | M59: À tester
A60: TC-STK-006 | B60: STK Stock | C60: SRS 9.2 | D60: Droit spécifique pour bloquer et débloquer | E60: Boutique / lecture seule | F60: Un compte avec « stock : voir » seulement. | G60: 1. Tenter de bloquer et de débloquer par l'écran, puis par l'API. | H60: Aucun bouton n'est proposé et l'API répond 403. Un châssis hors périmètre répond 404. | I60: Droits et périmètre | J60: M | K60: Livré | L60: StockTest | M60: À tester
A61: TC-STK-007 | B61: STK Stock | C61: EF-STK-05 | D61: Journal des mouvements par châssis, modèle, emplacement, type et période | E61: Contrôleur, Direction | F61: Plusieurs mouvements sur une moto (réception, blocage, déblocage, transfert). | G61: 1. Stock > Mouvements : rechercher par numéro de châssis. 2. Filtrer par modèle, emplacement, type, période. 3. Cliquer sur un châssis. | H61: Les mouvements s'affichent du plus récent au plus ancien avec statut avant/après, emplacements, motif et auteur. Le périmètre limite les lignes visibles. Les mouvements sont en ajout seul. | I61: Fonctionnel | J61: M | K61: Livré | L61: StockTest | M61: À tester
A62: TC-STK-008 | B62: STK Stock | C62: EF-STK-04 | D62: Aucun écran ni appel de modification directe d'une quantité | E62: Administrateur | F62: — | G62: 1. Parcourir les écrans de stock : chercher un champ de saisie de quantité. 2. Tenter PUT/POST/DELETE sur les ressources de stock et de mouvements par l'API. | H62: Aucune saisie de quantité n'existe. Les appels de modification répondent 4xx. Tout mouvement vient d'une opération (réception, transfert, blocage, import). | I62: Règle de gestion | J62: M | K62: Livré | L62: StockTest | M62: À tester
A63: TC-STK-009 | B63: STK Stock | C63: US-046, EF-STK-08 | D63: Consulter le stock à une date passée | E63: Comptable | F63: Des mouvements sur plusieurs semaines. | G63: 1. Demander le stock à une date passée par modèle et emplacement. | H63: Non livré dans ce lot : le journal des mouvements est complet et en ajout seul, ce qui permet la reconstitution, mais l'écran « stock à date » est prévu au sprint de rapports. | I63: Fonctionnel | J63: M | K63: À livrer | M63: Non livré
A64: TC-STK-010 | B64: STK Stock | C64: EF-STK-09 | D64: Contrôle de cohérence nocturne emplacement/statut | E64: Contrôleur | F64: — | G64: 1. Provoquer en base une incohérence (châssis disponible sans emplacement) — impossible grâce aux contraintes. 2. Observer l'ouverture d'une anomalie. | H64: Non livré dans ce lot. Les contraintes de base (un emplacement courant, statut compatible avec l'emplacement) empêchent déjà l'incohérence ; la détection nocturne arrive avec le module Anomalies. | I64: Règle de gestion | J64: M | K64: À livrer | M64: Non livré
A65: TC-STK-011 | B65: STK Stock | C65: EF-STK-07 | D65: Ancienneté en stock par châssis | E65: Commercial, Direction | F65: Des motos en stock depuis plus de 90 jours. | G65: 1. Tableau de bord Commercial : bloc « À écouler en priorité ». 2. Liste des châssis : filtre d'ancienneté. 3. Rotation par modèle. | H65: L'ancienneté par châssis est livrée (liste, fiche, tableau de bord Commercial). La rotation par modèle n'est pas livrée. | I65: Fonctionnel | J65: S | K65: Partiel | L65: TableauDeBordMetierTest, ChassisTest | M65: À tester
A66: TC-STK-012 | B66: STK Stock | C66: EF-STK-11 | D66: Alerte de seuil de stock disponible par modèle et emplacement | E66: Responsable magasin | F66: — | G66: 1. Paramétrer un seuil minimal. 2. Descendre sous le seuil. | H66: Non livré dans ce lot (priorité « Pourrait »). | I66: Fonctionnel | J66: C | K66: À livrer | M66: Non livré
A67: TC-TRF-001 | B67: TRF Transferts | C67: US-043, EF-TRF-01, EF-TRF-03 | D67: Créer un transfert avec la liste obligatoire de châssis disponibles | E67: Magasinier | F67: Un magasin source avec 5 motos disponibles, 1 réservée ; une boutique destination. | G67: 1. Stock > Transferts > Nouveau. 2. Choisir source et destination ; valider sans châssis. 3. Scanner un châssis disponible, un réservé, un inconnu, un d'un autre site. 4. Cocher trois motos dans la liste, créer. 5. Vérifier le stock et les mouvements. | H67: Un transfert sans châssis est refusé. Les châssis non disponibles à la source sont refusés avec le motif par numéro. Le transfert « Initié » porte son numéro (TR-code-année-séquence). Aucun mouvement de stock n'est écrit (RG, EF-TRF-02). | I67: Fonctionnel | J67: M | K67: Livré | L67: TransfertsTest | M67: À tester
A68: TC-TRF-002 | B68: TRF Transferts | C68: EF-TRF-01 | D68: Un châssis ne figure que dans un transfert en cours | E68: Magasinier | F68: Un transfert initié contenant le châssis X. | G68: 1. Créer un second transfert avec X. 2. Ouvrir la liste des châssis proposés à la création. 3. Annuler le premier transfert puis recommencer. | H68: Le second transfert est refusé (« déjà dans un autre transfert »). X n'est plus proposé. Après annulation du premier, X est de nouveau libre. | I68: Règle de gestion | J68: M | K68: Livré | L68: TransfertsTest | M68: À tester
A69: TC-TRF-003 | B69: TRF Transferts | C69: EF-TRF-02, US-043 | D69: Expédier : sortie de la source et passage en transit interne | E69: Magasinier (source) | F69: Un transfert initié de 3 motos. | G69: 1. Expédier depuis un compte de la destination seulement (doit être refusé). 2. Expédier depuis la source : confirmer. 3. Consulter le stock source, le stock global, le statut et l'emplacement des châssis, les mouvements. 4. Télécharger le bon de transfert. | H69: Le stock de la source baisse de 3. Les motos sont « En transit interne » dans l'emplacement de transit : comptées ni à la source ni à la destination. Des mouvements « Transfert expédié » sont écrits. Le bon PDF liste les châssis et les signatures. Le personnel de la destination est notifié. | I69: Fonctionnel | J69: M | K69: Livré | L69: TransfertsTest | M69: À tester
A70: TC-TRF-004 | B70: TRF Transferts | C70: US-044, EF-TRF-04 | D70: Réceptionner par scan : manquant en transit, non prévu refusé, anomalie A12 | E70: Vendeur boutique (destination) | F70: Un transfert expédié de 10 motos. | G70: 1. En destination : ouvrir le transfert > Réception par pointage. 2. Pointer 9 motos du transfert et 1 moto non prévue. 3. Cocher « Clôturer avec un écart » et confirmer. 4. Consulter le stock destination, la moto manquante, l'anomalie, les notifications du contrôle. | H70: Le stock de la destination augmente des 9 motos pointées. La moto manquante reste EN TRANSIT INTERNE et l'anomalie A12 est ouverte avec le coût des motos manquantes. La moto non prévue est refusée, signalée et tracée. Le contrôle est notifié. | I70: Fonctionnel | J70: M | K70: Livré | L70: TransfertsTest | M70: À tester
A71: TC-TRF-005 | B71: TRF Transferts | C71: EF-TRF-05, RG-19 | D71: Expéditeur et réceptionnaire différents (paramétrable) | E71: Magasinier (expédie), Compte des deux sites | F71: Un compte rattaché aux deux sites ; paramètre « Transfert réceptionné par un autre utilisateur » = Oui. | G71: 1. Avec ce compte : créer, expédier puis tenter de réceptionner. 2. Passer le paramètre à Non et recommencer. 3. Remettre Oui. | H71: Avec Oui, la réception par le même utilisateur est refusée (le panneau de pointage n'est pas proposé, l'API répond 403). Avec Non elle passe. | I71: Règle de gestion | J71: M | K71: Livré | L71: TransfertsTest | M71: À tester
A72: TC-TRF-006 | B72: TRF Transferts | C72: EF-TRF-10 | D72: Réception en plusieurs fois | E72: Vendeur boutique | F72: Un transfert expédié de 3 motos. | G72: 1. Pointer et confirmer 1 moto sans cocher la clôture. 2. Revenir plus tard : pointer les 2 autres. 3. Repointer une moto déjà reçue. | H72: Le transfert reste « Expédié » avec « 1 / 3 » puis passe « Réceptionné ». Une moto déjà reçue est refusée (« déjà réceptionné »), jamais comptée deux fois. L'expéditeur est notifié de la fin. | I72: Fonctionnel | J72: S | K72: Livré | L72: TransfertsTest | M72: À tester
A73: TC-TRF-007 | B73: TRF Transferts | C73: EF-TRF-07 | D73: Annuler avant l'expédition, corriger ensuite par un transfert retour | E73: Magasinier | F73: Un transfert initié et un transfert expédié. | G73: 1. Annuler le transfert initié (sans motif, puis avec). 2. Tenter d'annuler le transfert expédié. 3. Depuis le transfert expédié : « Transfert retour ». | H73: L'annulation exige un motif et libère les châssis. Après expédition elle est refusée avec l'indication de créer un transfert retour. Le retour préremplit le sens inverse et référence l'original. | I73: Règle de gestion | J73: M | K73: Livré | L73: TransfertsTest | M73: À tester
A74: TC-TRF-008 | B74: TRF Transferts | C74: US-045, EF-TRF-08 | D74: Alerte et anomalie pour transfert non réceptionné après le délai | E74: Contrôleur | F74: Paramètre « Délai de réception d'un transfert » = 5 jours ; un transfert expédié il y a plus de 5 jours (voir note). | G74: 1. Attendre le contrôle quotidien de 7 h (ou faire exécuter le contrôle par l'équipe technique en recette). 2. Se connecter en contrôleur : notifications. 3. Ouvrir le transfert. 4. Relancer le contrôle. 5. Supprimer le paramètre : refaire. | H74: Le contrôleur reçoit une alerte, l'anomalie A12 est ouverte (une seule par transfert) et le transfert est marqué « En retard ». Une seconde exécution ne réalerte pas. Sans délai paramétré, aucun contrôle n'est appliqué. | I74: Fonctionnel | J74: M | K74: Livré | L74: TransfertsTest | M74: À tester
A75: TC-TRF-009 | B75: TRF Transferts | C75: EF-TRF-09 | D75: Listes « à expédier » chez la source et « à réceptionner » chez la destination | E75: Magasinier, Vendeur boutique | F75: Un transfert initié et un transfert expédié entre le magasin et la boutique. | G75: 1. En magasinier : Transferts > À expédier / À réceptionner. 2. En vendeur boutique : idem. | H75: Un transfert initié est « à expédier » chez la source seulement. Un transfert expédié est « à réceptionner » chez la destination seulement. | I75: Fonctionnel | J75: M | K75: Livré | L75: TransfertsTest | M75: À tester
A76: TC-TRF-010 | B76: TRF Transferts | C76: EF-ADM-13, SRS 9.2 | D76: Périmètre et droits des transferts | E76: Magasinier d'un autre site, Commercial | F76: Un transfert entre A et B. | G76: 1. En compte du site C : ouvrir le transfert (écran et API). 2. En commercial : lister les transferts. 3. En boutique : tenter d'expédier. | H76: Transfert d'un autre site : introuvable. Commercial : 403. La boutique crée et réceptionne mais n'expédie pas (droit « valider » réservé au magasin). | I76: Droits et périmètre | J76: M | K76: Livré | L76: TransfertsTest | M76: À tester
A77: TC-TRF-011 | B77: TRF Transferts | C77: EF-TRF-06 | D77: Bon de transfert signé archivé | E77: Magasinier | F77: Un transfert expédié ; module Documents. | G77: 1. Imprimer le bon, le faire signer, le scanner et le joindre au transfert. | H77: Le bon PDF est livré ; l'archivage du bon signé arrive avec le module Documents. | I77: Fonctionnel | J77: M | K77: Partiel | L77: TransfertsTest | M77: À tester
A78: TC-REP-001 | B78: REP Reprise du stock | C78: US-006, SRS 14.2 | D78: Importer le stock initial par châssis (simulation puis import réel) | E78: Administrateur | F78: Le modèle Excel téléchargé, rempli avec le jeu de données de l'onglet « Jeu de données import » ; magasin et boutiques créés ; modèles au catalogue. | G78: 1. Stock > Import du stock initial > Télécharger le modèle. 2. Charger le fichier en simulation : lire le rapport. 3. Décocher « Simulation » et importer. 4. Lire le rapport, l'historique, le stock par emplacement. | H78: La simulation ne crée rien. L'import crée chaque moto à son emplacement (disponible ou bloquée), avec date d'entrée, coût et mouvement « Stock initial ». Les lignes fautives sont rejetées avec numéro de ligne et motif (voir l'onglet de données). Le rapport est conservé. | I78: Fonctionnel | J78: M | K78: Livré | L78: StockInitialTest | M78: À tester
... A83: TC-REP-006 | B83: REP Reprise du stock | C83: SRS 14.2 | D83: Périmètre et droits du pointage | E83: Magasinier d'un autre site, lecture seule | F83: Un rapprochement réalisé sur le site A. | G83: 1. En compte du site B : ouvrir le rapport du site A, lister les rapprochements, tenter de pointer le site A. 2. En compte sans « inventaires : créer » : tenter de pointer. | H83: Le rapport du site A est introuvable depuis B, la liste est vide, le pointage du site A est refusé (404). Sans le droit : 403. | I83: Droits et périmètre | J83: M | K83: Livré | L83: StockInitialTest | M83: À tester
A84: TC-REP-007 | B84: REP Reprise du stock | C84: SRS 14.2 | D84: Bascule site par site : magasin et boutique pilote d'abord | E84: Direction, Administrateur | F84: Données de reprise validées. | G84: 1. Importer et rapprocher le magasin. 2. Importer et rapprocher la boutique pilote. 3. Deux semaines plus tard, la seconde boutique. | H84: Chaque site a un rapprochement à écart nul avant sa mise en service. Voir la checklist de l'onglet « Reprise des données ». | I84: Fonctionnel | J84: M | K84: Livré | M84: À tester
A85: TC-TRV-001 | B85: TRV Transverse | C85: RG-02, EF-CAT-04 | D85: Un seul emplacement courant par châssis | E85: Administrateur technique | F85: Accès à la base de recette. | G85: 1. Examiner le schéma : un champ emplacement unique par châssis. 2. Tenter en base de créer une moto disponible sans emplacement, ou une moto « en transit fournisseur » avec emplacement. | H85: Les contraintes de base refusent ces états. Aucune moto n'est disponible à deux endroits. | I85: Règle de gestion | J85: M | K85: Livré | L85: ChassisTest | M85: À tester
A86: TC-TRV-002 | B86: TRV Transverse | C86: RG-18, US-155 | D86: Aucune suppression des opérations sensibles | E86: Direction | F86: Une réception validée, un transfert expédié, des mouvements, un règlement (lot 2). | G86: 1. Parcourir les écrans : chercher un bouton Supprimer. 2. Appeler DELETE sur les ressources (réceptions validées, transferts, mouvements, journal d'audit, prix). | H86: Aucun bouton Supprimer sur les opérations sensibles (seul le retrait d'un châssis d'un brouillon de réception est permis, sans effet sur le stock). Les appels de suppression sont refusés ; la correction passe par annulation (avant expédition), retour ou ajustement tracés. | I86: Règle de gestion | J86: M | K86: Livré | L86: StockTest, ChassisTest | M86: À tester
A87: TC-TRV-003 | B87: TRV Transverse | C87: AUD-01, DoD | D87: Les opérations clés figurent au journal avec valeurs avant et après | E87: Équipe technique, Direction | F87: Avoir joué TC-REC-006, TC-TRF-003, TC-STK-004, TC-REP-001. | G87: 1. Pour chaque opération, retrouver sa ligne dans la table journal_audit (ou l'activité récente du tableau de bord Administration). 2. Lire action, auteur, date, valeurs avant/après, motif. | H87: Chaque opération (réception validée, transfert expédié/réceptionné, blocage, import, rapprochement, annulation) a sa ligne complète. | I87: Audit et traçabilité | J87: M | K87: Partiel | L87: ReceptionsTest, TransfertsTest, StockTest, StockInitialTest | M87: À tester
A88: TC-TRV-004 | B88: TRV Transverse | C88: SRS 10.9, ENF sécurité | D88: Protection de l'API : authentification, CSRF, droits par appel direct | E88: Testeur sécurité | F88: Un outil de test HTTP. | G88: 1. Appeler les endpoints sans session (attendu 401). 2. Appeler une écriture avec session mais sans jeton CSRF. 3. Appeler avec une session de profil insuffisant (403). 4. Tenter une injection dans les champs de recherche. | H88: 401 sans session, écriture refusée sans CSRF, 403 hors droit. Les recherches sont paramétrées (aucune injection). Les erreurs ne divulguent ni trace ni détail technique. | I88: Non fonctionnel | J88: M | K88: Livré | L88: SecuriteTest, GestionnaireErreursTest | M88: À tester
A89: TC-TRV-005 | B89: TRV Transverse | C89: ENF-06, SRS 11 | D89: Performance : stock et listes avec un volume réaliste | E89: Équipe technique | F89: Base chargée à 30 000 châssis et 15 emplacements (cible de dimensionnement H4). | G89: 1. Charger des données de volume. 2. Mesurer le temps de réponse de : synthèse du stock, liste des châssis (page de 15), fiche châssis, journal des mouvements, import de 5 000 lignes. | H89: À mesurer : cible à confirmer avec VITRACO (objectif indicatif < 2 s pour les écrans de consultation, < 3 s pour la chaîne complète d'un châssis). Résultat à consigner dans le commentaire. | I89: Non fonctionnel | J89: M | K89: Livré | M89: À tester
A90: TC-TRV-006 | B90: TRV Transverse | C90: DoD, SRS 11 | D90: Ergonomie : écran utilisable sur ordinateur et sur téléphone | E90: Magasinier | F90: Un ordinateur et un téléphone. | G90: 1. Parcourir : stock, réception (scan), transfert (pointage), pointage d'ouverture, import. 2. Vérifier lisibilité, défilement horizontal, boutons accessibles au doigt. | H90: Aucun défilement horizontal de la page, champs de scan larges, tableaux défilables. Les textes sont en français. | I90: Non fonctionnel | J90: M | K90: Partiel | M90: À tester
A91: TC-TRV-007 | B91: TRV Transverse | C91: SRS 11 | D91: Compatibilité navigateurs | E91: Testeur | F91: Chrome, Edge, Safari et Firefox récents. | G91: 1. Rejouer TC-REC-002 et TC-TRF-004 sur chaque navigateur. | H91: Même comportement, mêmes résultats, aucune erreur console. | I91: Non fonctionnel | J91: S | K91: Livré | M91: À tester
A92: TC-TRV-008 | B92: TRV Transverse | C92: SRS 10.8 | D92: Installation à partir d'une base vide : migrations | E92: Équipe technique | F92: Une base PostgreSQL vide. | G92: 1. Démarrer l'application. 2. Vérifier l'application des migrations V1 à V14, le premier administrateur, les rôles et permissions par défaut, l'emplacement de transit. | H92: L'application démarre sans erreur, toutes les migrations passent, l'administrateur est amorcé, les 8 rôles livrés existent. | I92: Non fonctionnel | J92: M | K92: Livré | L92: VitracosarlApiApplicationTests | M92: À tester

Sheet Recette Lot 1
A1: Scénarios de recette de bout en bout — Lot 1
A2: Chaque scénario se joue dans l'ordre, avec des comptes distincts quand le profil change. Renseigner Résultat, Date, Testeur et la preuve (capture d'écran, n° de document).
A4: Scénario | B4: Étape | C4: Action | D4: Profil | E4: Résultat attendu | F4: Réf. SRS | G4: Résultat | H4: Date | I4: Testeur | J4: Preuve / commentaire
A5: RV1-01 · Reprise du stock d'un site : import puis pointage à écart nul (jalon V1)
A6: RV1-01 | B6: 1 | C6: Créer le magasin, la boutique pilote et vérifier les modèles au catalogue. | D6: Administrateur | E6: Emplacements et modèles disponibles, prix renseignés. | F6: SRS 14.2 | G6: À faire
A7: RV1-01 | B7: 2 | C7: Remplir le modèle Excel avec l'inventaire d'ouverture du magasin (≥ 50 motos) et lancer la simulation. | D7: Administrateur | E7: Rapport sans rien créer ; les lignes fautives sont listées avec leur motif. | F7: SRS 14.2 | G7: À faire
A8: RV1-01 | B8: 3 | C8: Corriger le fichier et importer pour de bon. | D8: Administrateur | E8: Toutes les motos sont au stock du magasin ; le rapport est conservé. | F8: SRS 14.2 | G8: À faire
A9: RV1-01 | B9: 4 | C9: Compter physiquement le magasin au scan et pointer. | D9: Magasinier | E9: Rapport de rapprochement : manquants et inattendus identifiés. | F9: SRS 14.2 | G9: À faire
A10: RV1-01 | B10: 5 | C10: Traiter les écarts (corriger le fichier ou le comptage) et pointer de nouveau. | D10: Magasinier | E10: Écart nul : stock d'ouverture validé pour le site. | F10: SRS 14.2 | G10: À faire
A11: RV1-01 | B11: 6 | C11: Répéter pour la boutique pilote puis pour la seconde boutique. | D11: Vendeur boutique | E11: Écart nul sur chacun des sites. | F11: SRS 14.2 | G11: À faire
A12: RV1-02 · R1 (partie lot 1) : commande fournisseur, colisage, dédouanement, réception de 100 châssis
A13: RV1-02 | B13: 1 | C13: Créer une commande fournisseur de 100 motos (plusieurs modèles). | D13: Acheteur | E13: Statut COMMANDÉE, stock inchangé. | F13: R1 (partiel) | G13: À faire
A14: RV1-02 | B14: 2 | C14: Confirmer, importer le colisage de 100 lignes, saisir arrivée, frais avec pièces. | D14: Acheteur | E14: 100 châssis « En transit fournisseur » ; coût provisoire calculé ; frais sans pièce signalé. | F14: R1 (partiel) | G14: À faire
A15: RV1-02 | B15: 3 | C15: Terminer le dédouanement de l'arrivage et avancer la commande. | D15: Acheteur | E15: Commande « À réceptionner » ; châssis « À réceptionner » ; magasin notifié. | F15: R1 (partiel) | G15: À faire
A16: RV1-02 | B16: 4 | C16: Ouvrir la réception et scanner les 100 châssis. | D16: Magasinier | E16: Compteurs attendu/reçu/écart à jour sans scan perdu. | F16: R1 (partiel) | G16: À faire
A17: RV1-02 | B17: 5 | C17: Valider la réception par un second utilisateur. | D17: Responsable magasin | E17: Stock physique du magasin +100, 100 disponibles, mouvements écrits, PV généré, commande « Réceptionnée ». | F17: R1 (partiel) | G17: À faire
A18: RV1-02 | B18: 6 | C18: Contrôler le stock global et la fiche de 3 châssis. | D18: Direction | E18: 100 physiques, 100 disponibles ; historiques complets. (La suite R1 — commande client, facture, livraison — se joue au lot 2.) | F18: R1 (partiel) | G18: À faire
A19: RV1-03 · R6 : transfert de 10 motos dont 9 reçues
A20: RV1-03 | B20: 1 | C20: Créer un transfert de 10 motos du magasin vers la boutique. | D20: Magasinier | E20: Transfert « Initié », stock inchangé. | F20: R6 | G20: À faire
A21: RV1-03 | B21: 2 | C21: Expédier le transfert et éditer le bon. | D21: Responsable magasin | E21: Stock source −10 ; 10 motos « En transit interne » ; bon PDF ; boutique notifiée. | F21: R6 | G21: À faire
A22: RV1-03 | B22: 3 | C22: Réceptionner par pointage 9 motos, clôturer avec écart. | D22: Vendeur boutique | E22: 9 motos en stock à la destination ; 1 en transit interne. | F22: R6 | G22: À faire
A23: RV1-03 | B23: 4 | C23: Consulter l'anomalie et les notifications. | D23: Contrôleur | E23: Anomalie A12 ouverte avec le coût de la moto manquante ; alerte reçue. | F23: R6 | G23: À faire
A24: RV1-03 | B24: 5 | C24: Contrôler la fiche de la moto manquante et le stock global. | D24: Direction | E24: Moto « En transit interne » comptée une seule fois dans le global. | F24: R6 | G24: À faire
A25: RV1-04 · R10 (partie lot 1) : contrôle des droits et du périmètre
A26: RV1-04 | B26: 1 | C26: Se connecter en commercial : ouvrir catalogue, stock, fiche châssis. | D26: Commercial | E26: Aucun coût de revient ni prix d'achat visible, ni sur l'écran ni par l'API. | F26: R10 (partiel) | G26: À faire
A27: RV1-04 | B27: 2 | C27: Se connecter en magasinier d'un site : consulter le stock, un transfert, une réception d'un autre site. | D27: Magasinier | E27: Seul son périmètre est visible ; les objets d'un autre site sont introuvables. | F27: R10 (partiel) | G27: À faire
A28: RV1-04 | B28: 3 | C28: Se connecter en contrôleur : tenter de modifier un stock, de valider une réception. | D28: Contrôleur | E28: Lecture seule sur ces modules ; blocage et corrections selon ses droits spécifiques. | F28: R10 (partiel) | G28: À faire
A29: RV1-04 | B29: 4 | C29: Retirer un droit à un rôle et refaire l'action par un appel direct à l'API. | D29: Administrateur | E29: Refus 403 ; modification tracée ; Direction notifiée. | F29: R10 (partiel) | G29: À faire
A30: RV1-05 · Réception en plusieurs fois, avec moto endommagée et moto non annoncée
A31: RV1-05 | B31: 1 | C31: Ouvrir une réception d'un arrivage de 5 motos annoncées ; scanner 3 conformes, 1 endommagée, 1 non annoncée. | D31: Magasinier | E31: Messages de contrôle à chaque cas ; justification et description exigées. | F31: REC, STK | G31: À faire
A32: RV1-05 | B32: 2 | C32: Valider par un second utilisateur. | D32: Responsable magasin | E32: 2 disponibles, 1 bloquée, 1 inattendue disponible ; commande « Réception partielle » avec reliquat ; contrôleur notifié. | F32: REC, STK | G32: À faire
A33: RV1-05 | B33: 3 | C33: Recevoir le reliquat dans une seconde réception. | D33: Magasinier | E33: Commande « Réceptionnée » quand tout est reçu ; deux PV distincts. | F33: REC, STK | G33: À faire
A34: RV1-05 | B34: 4 | C34: Bloquer puis débloquer une moto en litige. | D34: Responsable magasin | E34: Motif et pièce exigés ; historique de la fiche à jour. | F34: REC, STK | G34: À faire
A35: RV1-06 · Correction d'un numéro de châssis et traçabilité complète d'une moto
A36: RV1-06 | B36: 1 | C36: Demander la correction d'un numéro mal saisi. | D36: Responsable magasin | E36: Demande « en attente ». | F36: US-013, US-012 | G36: À faire
A37: RV1-06 | B37: 2 | C37: Tenter de la valider avec le même compte puis avec un collègue. | D37: Responsable magasin, Magasinier | E37: Refus puis validation ; l'ancien numéro reste trouvable. | F37: US-013, US-012 | G37: À faire
A38: RV1-06 | B38: 3 | C38: Ouvrir la fiche : lire l'histoire depuis la création à la réception puis au transfert. | D38: Direction | E38: Chaque événement daté, avec auteur et statuts avant/après. | F38: US-013, US-012 | G38: À faire
A39: RV1-06 | B39: 4 | C39: Rechercher la moto par l'ancien numéro. | D39: Magasinier | E39: La fiche s'ouvre ; l'ancien numéro est signalé. | F39: US-013, US-012 | G39: À faire
A40: RV1-07 · Séparation des tâches et non-suppression
A41: RV1-07 | B41: 1 | C41: Même utilisateur : ouvrir et valider une réception ; expédier et réceptionner un transfert. | D41: Magasinier | E41: Refus dans les deux cas (paramètres à Oui). | F41: RG-18, RG-19 | G41: À faire
A42: RV1-07 | B42: 2 | C42: Passer les deux paramètres à Non et rejouer. | D42: Administrateur | E42: Les opérations passent ; changement de paramètre historisé ; remettre Oui. | F42: RG-18, RG-19 | G42: À faire
A43: RV1-07 | B43: 3 | C43: Tenter de supprimer réception validée, transfert, mouvement, journal par l'API. | D43: Direction | E43: Refus ; aucune suppression possible ; annulation/retour tracés. | F43: RG-18, RG-19 | G43: À faire

Sheet Reprise des données
A1: Reprise des données — Lot 1
A2: Source : SRS 14.2. La bascule se fait site par site : le magasin et une boutique pilote d'abord, la seconde boutique deux semaines plus tard.
A4: Donnée | B4: Source | C4: Méthode | D4: Contrôle de validation | E4: Responsable | F4: Outil livré / remarque | G4: Statut | H4: Date de validation | I4: Validé par
A5: Modèles et prix | B5: Fichiers commerciaux | C5: Import Excel (saisie à l'écran en attendant) | D5: Relecture par le responsable commercial | E5: Responsable commercial | F5: Les modèles se créent un à un à l'écran dans ce lot ; l'import en masse des modèles n'est pas livré. | G5: À faire
A6: Stock par châssis | B6: Inventaire physique d'ouverture, par scan | C6: Import Excel (Stock > Import du stock initial) puis pointage | D6: Écart nul par site entre l'import et le comptage | E6: Magasinier + Administrateur | F6: Outils livrés : import avec simulation et rapport, pointage d'ouverture avec rapport conservé. | G6: À faire
A7: Arrivages en cours | B7: Dossiers d'importation | C7: Saisie (commandes, arrivages, colisage) | D7: Relecture par la Direction | E7: Acheteur | F7: Les commandes et arrivages en cours se saisissent à l'écran ; le colisage s'importe en CSV/Excel. | G7: À faire
A8: Utilisateurs, rôles et emplacements | B8: Organisation de VITRACO | C8: Saisie | D8: Validation par la Direction | E8: Administrateur | F8: Les 8 rôles livrés sont à ajuster ; le second facteur est à activer pour Administrateur, Direction et Comptabilité. | G8: À faire
A9: Fournisseurs et référentiels | B9: Fichiers commerciaux et comptables | C9: Saisie | D9: Relecture par la comptabilité | E9: Administrateur | F9: Fournisseurs, banques, modes de paiement, catégories de dépense, centres de coût. | G9: À faire
A10: Paramètres de contrôle et fiscaux | B10: Direction et comptabilité | C10: Saisie (Paramètres) | D10: Validation par la Direction | E10: Direction | F10: Les seuils et délais non fixés désactivent le contrôle correspondant ; taux fiscaux à confirmer avec la DGI. | G10: À faire
A13: Rapprochement du stock d'ouverture, site par site
A14: Reporter ici, pour chaque site, les chiffres du dernier rapport de l'écran Stock > Pointage d'ouverture. « Écart nul » est calculé : il faut zéro manquant et zéro inattendu avec un pointage renseigné.
A16: Site | B16: Type | C16: Date de l'import | D16: Motos importées | E16: Motos pointées | F16: Manquantes | G16: Inattendues | H16: Écart nul ? | I16: Validé par la Direction
A17: Magasin principal | B17: Magasin | H17: =IF(AND(E17<>"",F17=0,G17=0),"Oui","Non")
A18: Boutique pilote | B18: Boutique | H18: =IF(AND(E18<>"",F18=0,G18=0),"Oui","Non")
A19: Seconde boutique (J+14) | B19: Boutique | H19: =IF(AND(E19<>"",F19=0,G19=0),"Oui","Non")
A21: Rappel : le pointage ne corrige rien. Un écart se traite en corrigeant le fichier d'import (puis en réimportant les seules lignes manquantes) ou, en production, par un ajustement validé par un second utilisateur (module des ajustements, lot ultérieur).

Sheet Jeu de données import
A1: Jeu de données — import du stock initial (TC-REP-001, TC-REP-002)
A2: Recopier ces lignes dans le modèle Excel (Stock > Import du stock initial > Télécharger le modèle), après avoir remplacé les valeurs entre chevrons.
A4: Cas | B4: numero_chassis | C4: code_article | D4: emplacement | E4: statut | F4: date_entree | G4: cout_revient | H4: motif_blocage | I4: Résultat attendu
A5: Ligne valide, avec date, coût et couleur | B5: LWBTEST00000000001 | C5: <CODE_ARTICLE> | D5: <CODE_MAGASIN> | E5: disponible | F5: 01/09/2026 | G5: 980000 | I5: Importée
A6: Ligne valide, valeurs par défaut | B6: LWBTEST00000000002 | C6: <CODE_ARTICLE> | D6: <CODE_BOUTIQUE> | I6: Importée (statut disponible, date du jour)
A7: Moto bloquée avec motif | B7: LWBTEST00000000003 | C7: <CODE_ARTICLE> | D7: <CODE_MAGASIN> | E7: bloqué | H7: Cadre fissuré | I7: Importée BLOQUÉE avec son motif
A8: Emplacement donné par son nom | B8: LWBTEST00000000004 | C8: <CODE_ARTICLE> | D8: <NOM_BOUTIQUE> | G8: 1 250 000 | I8: Importée (coût 1 250 000 lu malgré les espaces)
A9: Numéro avec tirets et minuscules | B9: lwb-test-0000-0000-05 | C9: <CODE_ARTICLE> | D9: <CODE_MAGASIN> | I9: Importée (numéro normalisé en majuscules sans tirets)
A10: Doublon dans le fichier | B10: LWBTEST00000000001 | C10: <CODE_ARTICLE> | D10: <CODE_MAGASIN> | I10: Rejetée : doublon dans le fichier
A11: Châssis déjà au stock | B11: <NUMERO_DEJA_EN_STOCK> | C11: <CODE_ARTICLE> | D11: <CODE_MAGASIN> | I11: Rejetée : châssis déjà enregistré (avec son emplacement)
A12: Code article inconnu | B12: LWBTEST00000000006 | C12: ZZ-INCONNU | D12: <CODE_MAGASIN> | I12: Rejetée : code article inconnu : ZZ-INCONNU
A13: Emplacement inconnu | B13: LWBTEST00000000007 | C13: <CODE_ARTICLE> | D13: LIEU-FANTOME | I13: Rejetée : emplacement inconnu, désactivé ou qui n'est ni un magasin ni une boutique
A14: Emplacement de transit | B14: LWBTEST00000000008 | C14: <CODE_ARTICLE> | D14: TRANSIT | I14: Rejetée : ni un magasin ni une boutique
A15: Bloqué sans motif | B15: LWBTEST00000000009 | C15: <CODE_ARTICLE> | D15: <CODE_MAGASIN> | E15: bloqué | I15: Rejetée : un châssis bloqué exige un motif
A16: Statut non repris | B16: LWBTEST00000000010 | C16: <CODE_ARTICLE> | D16: <CODE_MAGASIN> | E16: réservée | I16: Rejetée : statut non repris
A17: Date illisible | B17: LWBTEST00000000011 | C17: <CODE_ARTICLE> | D17: <CODE_MAGASIN> | F17: 31/02/2026 | I17: Rejetée : date d'entrée illisible
A18: Date dans le futur | B18: LWBTEST00000000012 | C18: <CODE_ARTICLE> | D18: <CODE_MAGASIN> | F18: <DATE_DEMAIN> | I18: Rejetée : date d'entrée dans le futur
A19: Coût négatif | B19: LWBTEST00000000013 | C19: <CODE_ARTICLE> | D19: <CODE_MAGASIN> | G19: -5 | I19: Rejetée : coût de revient négatif
A20: Format de châssis non conforme au modèle | B20: XX1 | C20: <CODE_ARTICLE> | D20: <CODE_MAGASIN> | I20: Rejetée : numéro ne respectant pas le format du modèle (si un format est défini)
A21: Numéro manquant | C21: <CODE_ARTICLE> | D21: <CODE_MAGASIN> | I21: Rejetée : numéro de châssis manquant
A22: Ligne entièrement vide | I22: Ignorée (ni importée, ni rejetée, non comptée)
A24: Remplacements : <CODE_ARTICLE> = un code article existant au catalogue ; <CODE_MAGASIN> et <CODE_BOUTIQUE> = codes d'emplacement existants (ou leur nom) ; <NOM_BOUTIQUE> = nom complet de la boutique ;
A25: <NUMERO_DEJA_EN_STOCK> = le numéro d'un châssis déjà au stock ; <DATE_DEMAIN> = la date de demain au format jj/mm/aaaa.
A26: Résultat attendu de l'ensemble : 5 lignes importées, 12 lignes rejetées avec leur motif, 1 ligne vide ignorée. Rejouer ensuite le fichier : 0 ligne importée (aucun doublon).
A27: Colonnes obligatoires : numero_chassis, code_article, emplacement. Facultatives : statut (disponible par défaut, ou bloqué avec motif), date_entree, cout_revient, numero_moteur, couleur, motif_blocage. Formats : .xlsx ou .csv (séparateur ; , ou tabulation).

Sheet Traçabilité
A1: Traçabilité — user stories du lot 1
A2: Le nombre de cas et leur résultat sont calculés à partir de l'onglet « Plan de test » (colonne Référence).
A4: Story | B4: Epic | C4: Intitulé | D4: Critères d'acceptation (SRS) | E4: Livraison | F4: Cas | G4: Réussis | H4: Échecs | I4: Reste | J4: Verdict | K4: Commentaire
A5: US-001 | B5: EP-01 | C5: Créer un utilisateur avec ses rôles et ses emplacements | D5: Lien d'activation ; ne voit que ses emplacements ; création au journal | E5: Livré | F5: =COUNTIF('Plan de test'!$C$5:$C$152,"*"&A5&"*") | G5: =COUNTIFS('Plan de test'!$C$5:$C$152,"*"&A5&"*",'Plan de test'!$M$5:$M$152,"Réussi") | H5: =COUNTIFS('Plan de test'!$C$5:$C$152,"*"&A5&"*",'Plan de test'!$M$5:$M$152,"Échec")+COUNTIFS('Plan de test'!$C$5:$C$152,"*"&A5&"*",'Plan de test'!$M$5:$M$152,"Bloqué") | I5: =F5-G5-H5-COUNTIFS('Plan de test'!$C$5:$C$152,"*"&A5&"*",'Plan de test'!$M$5:$M$152,"Non livré") | J5: =IF(F5=0,"Aucun cas",IF(H5>0,"Échec",IF(G5=F5,"Validée",IF(G5+COUNTIFS('Plan de test'!$C$5:$C$152,"*"&A5&"*",'Plan de test'!$M$5:$M$152,"Non livré")=F5,"Non livrée","En cours"))))
A6: US-002 | B6: EP-01 | C6: Connexion par mot de passe et second facteur | D6: 5 échecs verrouillent ; second facteur pour Administrateur, Direction, Comptabilité | E6: Livré | F6: =COUNTIF('Plan de test'!$C$5:$C$152,"*"&A6&"*") | G6: =COUNTIFS('Plan de test'!$C$5:$C$152,"*"&A6&"*",'Plan de test'!$M$5:$M$152,"Réussi") | H6: =COUNTIFS('Plan de test'!$C$5:$C$152,"*"&A6&"*",'Plan de test'!$M$5:$M$152,"Échec")+COUNTIFS('Plan de test'!$C$5:$C$152,"*"&A6&"*",'Plan de test'!$M$5:$M$152,"Bloqué") | I6: =F6-G6-H6-COUNTIFS('Plan de test'!$C$5:$C$152,"*"&A6&"*",'Plan de test'!$M$5:$M$152,"Non livré") | J6: =IF(F6=0,"Aucun cas",IF(H6>0,"Échec",IF(G6=F6,"Validée",IF(G6+COUNTIFS('Plan de test'!$C$5:$C$152,"*"&A6&"*",'Plan de test'!$M$5:$M$152,"Non livré")=F6,"Non livrée","En cours"))))
A7: US-003 | B7: EP-01 | C7: Régler les permissions d'un rôle action par action | D7: Retirer « Voir marges » masque les marges ; appel direct refusé | E7: Partiel | F7: =COUNTIF('Plan de test'!$C$5:$C$152,"*"&A7&"*") | G7: =COUNTIFS('Plan de test'!$C$5:$C$152,"*"&A7&"*",'Plan de test'!$M$5:$M$152,"Réussi") | H7: =COUNTIFS('Plan de test'!$C$5:$C$152,"*"&A7&"*",'Plan de test'!$M$5:$M$152,"Échec")+COUNTIFS('Plan de test'!$C$5:$C$152,"*"&A7&"*",'Plan de test'!$M$5:$M$152,"Bloqué") | I7: =F7-G7-H7-COUNTIFS('Plan de test'!$C$5:$C$152,"*"&A7&"*",'Plan de test'!$M$5:$M$152,"Non livré") | J7: =IF(F7=0,"Aucun cas",IF(H7>0,"Échec",IF(G7=F7,"Validée",IF(G7+COUNTIFS('Plan de test'!$C$5:$C$152,"*"&A7&"*",'Plan de test'!$M$5:$M$152,"Non livré")=F7,"Non livrée","En cours")))) | K7: Mécanisme livré et testé ; l'écran des marges viendra avec le lot 2
A8: US-004 | B8: EP-01 | C8: Créer magasins et boutiques, fixer le mode de chaque boutique | D8: Mode B exige un rattachement ; changement refusé s'il reste du stock | E8: Livré | F8: =COUNTIF('Plan de test'!$C$5:$C$152,"*"&A8&"*") | G8: =COUNTIFS('Plan de test'!$C$5:$C$152,"*"&A8&"*",'Plan de test'!$M$5:$M$152,"Réussi") | H8: =COUNTIFS('Plan de test'!$C$5:$C$152,"*"&A8&"*",'Plan de test'!$M$5:$M$152,"Échec")+COUNTIFS('Plan de test'!$C$5:$C$152,"*"&A8&"*",'Plan de test'!$M$5:$M$152,"Bloqué") | I8: =F8-G8-H8-COUNTIFS('Plan de test'!$C$5:$C$152,"*"&A8&"*",'Plan de test'!$M$5:$M$152,"Non livré") | J8: =IF(F8=0,"Aucun cas",IF(H8>0,"Échec",IF(G8=F8,"Validée",IF(G8+COUNTIFS('Plan de test'!$C$5:$C$152,"*"&A8&"*",'Plan de test'!$M$5:$M$152,"Non livré")=F8,"Non livrée","En cours")))) | K8: Contrôle du stock activé avec le lot 1
A9: US-005 | B9: EP-01 | C9: Paramétrer les seuils et délais de contrôle | D9: Nouvelle valeur applicable aux contrôles suivants ; ancienne au journal | E9: Livré | F9: =COUNTIF('Plan de test'!$C$5:$C$152,"*"&A9&"*") | G9: =COUNTIFS('Plan de test'!$C$5:$C$152,"*"&A9&"*",'Plan de test'!$M$5:$M$152,"Réussi") | H9: =COUNTIFS('Plan de test'!$C$5:$C$152,"*"&A9&"*",'Plan de test'!$M$5:$M$152,"Échec")+COUNTIFS('Plan de test'!$C$5:$C$152,"*"&A9&"*",'Plan de test'!$M$5:$M$152,"Bloqué") | I9: =F9-G9-H9-COUNTIFS('Plan de test'!$C$5:$C$152,"*"&A9&"*",'Plan de test'!$M$5:$M$152,"Non livré") | J9: =IF(F9=0,"Aucun cas",IF(H9>0,"Échec",IF(G9=F9,"Validée",IF(G9+COUNTIFS('Plan de test'!$C$5:$C$152,"*"&A9&"*",'Plan de test'!$M$5:$M$152,"Non livré")=F9,"Non livrée","En cours"))))
A10: US-006 | B10: EP-01 | C10: Importer les données initiales depuis Excel | D10: Lignes en erreur rejetées avec motif ; aucun doublon ; rapport d'import | E10: Partiel | F10: =COUNTIF('Plan de test'!$C$5:$C$152,"*"&A10&"*") | G10: =COUNTIFS('Plan de test'!$C$5:$C$152,"*"&A10&"*",'Plan de test'!$M$5:$M$152,"Réussi") | H10: =COUNTIFS('Plan de test'!$C$5:$C$152,"*"&A10&"*",'Plan de test'!$M$5:$M$152,"Échec")+COUNTIFS('Plan de test'!$C$5:$C$152,"*"&A10&"*",'Plan de test'!$M$5:$M$152,"Bloqué") | I10: =F10-G10-H10-COUNTIFS('Plan de test'!$C$5:$C$152,"*"&A10&"*",'Plan de test'!$M$5:$M$152,"Non livré") | J10: =IF(F10=0,"Aucun cas",IF(H10>0,"Échec",IF(G10=F10,"Validée",IF(G10+COUNTIFS('Plan de test'!$C$5:$C$152,"*"&A10&"*",'Plan de test'!$M$5:$M$152,"Non livré")=F10,"Non livrée","En cours")))) | K10: Stock par châssis livré ; les soldes clients et factures ouvertes viennent avec le lot 2
A11: US-007 | B11: EP-01 | C11: La Direction est notifiée de tout changement de droits | D11: Utilisateur, ancien et nouveau droit, auteur | E11: Livré | F11: =COUNTIF('Plan de test'!$C$5:$C$152,"*"&A11&"*") | G11: =COUNTIFS('Plan de test'!$C$5:$C$152,"*"&A11&"*",'Plan de test'!$M$5:$M$152,"Réussi") | H11: =COUNTIFS('Plan de test'!$C$5:$C$152,"*"&A11&"*",'Plan de test'!$M$5:$M$152,"Échec")+COUNTIFS('Plan de test'!$C$5:$C$152,"*"&A11&"*",'Plan de test'!$M$5:$M$152,"Bloqué") | I11: =F11-G11-H11-COUNTIFS('Plan de test'!$C$5:$C$152,"*"&A11&"*",'Plan de test'!$M$5:$M$152,"Non livré") | J11: =IF(F11=0,"Aucun cas",IF(H11>0,"Échec",IF(G11=F11,"Validée",IF(G11+COUNTIFS('Plan de test'!$C$5:$C$152,"*"&A11&"*",'Plan de test'!$M$5:$M$152,"Non livré")=F11,"Non livrée","En cours"))))
A12: US-008 | B12: EP-01 | C12: Recevoir ses tâches en attente en notification | D12: Un clic ouvre l'écran de traitement | E12: Livré | F12: =COUNTIF('Plan de test'!$C$5:$C$152,"*"&A12&"*") | G12: =COUNTIFS('Plan de test'!$C$5:$C$152,"*"&A12&"*",'Plan de test'!$M$5:$M$152,"Réussi") | H12: =COUNTIFS('Plan de test'!$C$5:$C$152,"*"&A12&"*",'Plan de test'!$M$5:$M$152,"Échec")+COUNTIFS('Plan de test'!$C$5:$C$152,"*"&A12&"*",'Plan de test'!$M$5:$M$152,"Bloqué") | I12: =F12-G12-H12-COUNTIFS('Plan de test'!$C$5:$C$152,"*"&A12&"*",'Plan de test'!$M$5:$M$152,"Non livré") | J12: =IF(F12=0,"Aucun cas",IF(H12>0,"Échec",IF(G12=F12,"Validée",IF(G12+COUNTIFS('Plan de test'!$C$5:$C$152,"*"&A12&"*",'Plan de test'!$M$5:$M$152,"Non livré")=F12,"Non livrée","En cours"))))
A13: US-010 | B13: EP-02 | C13: Créer un modèle avec ses prix | D13: Code article unique ; minimum ≤ vente | E13: Livré | F13: =COUNTIF('Plan de test'!$C$5:$C$152,"*"&A13&"*") | G13: =COUNTIFS('Plan de test'!$C$5:$C$152,"*"&A13&"*",'Plan de test'!$M$5:$M$152,"Réussi") | H13: =COUNTIFS('Plan de test'!$C$5:$C$152,"*"&A13&"*",'Plan de test'!$M$5:$M$152,"Échec")+COUNTIFS('Plan de test'!$C$5:$C$152,"*"&A13&"*",'Plan de test'!$M$5:$M$152,"Bloqué") | I13: =F13-G13-H13-COUNTIFS('Plan de test'!$C$5:$C$152,"*"&A13&"*",'Plan de test'!$M$5:$M$152,"Non livré") | J13: =IF(F13=0,"Aucun cas",IF(H13>0,"Échec",IF(G13=F13,"Validée",IF(G13+COUNTIFS('Plan de test'!$C$5:$C$152,"*"&A13&"*",'Plan de test'!$M$5:$M$152,"Non livré")=F13,"Non livrée","En cours"))))
A14: US-011 | B14: EP-02 | C14: Changer un prix avec une date d'effet | D14: Commandes validées gardent leur prix ; historique visible | E14: Partiel | F14: =COUNTIF('Plan de test'!$C$5:$C$152,"*"&A14&"*") | G14: =COUNTIFS('Plan de test'!$C$5:$C$152,"*"&A14&"*",'Plan de test'!$M$5:$M$152,"Réussi") | H14: =COUNTIFS('Plan de test'!$C$5:$C$152,"*"&A14&"*",'Plan de test'!$M$5:$M$152,"Échec")+COUNTIFS('Plan de test'!$C$5:$C$152,"*"&A14&"*",'Plan de test'!$M$5:$M$152,"Bloqué") | I14: =F14-G14-H14-COUNTIFS('Plan de test'!$C$5:$C$152,"*"&A14&"*",'Plan de test'!$M$5:$M$152,"Non livré") | J14: =IF(F14=0,"Aucun cas",IF(H14>0,"Échec",IF(G14=F14,"Validée",IF(G14+COUNTIFS('Plan de test'!$C$5:$C$152,"*"&A14&"*",'Plan de test'!$M$5:$M$152,"Non livré")=F14,"Non livrée","En cours")))) | K14: Historique livré ; commandes clients au lot 2
A15: US-012 | B15: EP-02 | C15: Fiche châssis : toute son histoire | D15: Statut, emplacement, événements datés avec auteur ; coût masqué sans permission | E15: Livré | F15: =COUNTIF('Plan de test'!$C$5:$C$152,"*"&A15&"*") | G15: =COUNTIFS('Plan de test'!$C$5:$C$152,"*"&A15&"*",'Plan de test'!$M$5:$M$152,"Réussi") | H15: =COUNTIFS('Plan de test'!$C$5:$C$152,"*"&A15&"*",'Plan de test'!$M$5:$M$152,"Échec")+COUNTIFS('Plan de test'!$C$5:$C$152,"*"&A15&"*",'Plan de test'!$M$5:$M$152,"Bloqué") | I15: =F15-G15-H15-COUNTIFS('Plan de test'!$C$5:$C$152,"*"&A15&"*",'Plan de test'!$M$5:$M$152,"Non livré") | J15: =IF(F15=0,"Aucun cas",IF(H15>0,"Échec",IF(G15=F15,"Validée",IF(G15+COUNTIFS('Plan de test'!$C$5:$C$152,"*"&A15&"*",'Plan de test'!$M$5:$M$152,"Non livré")=F15,"Non livrée","En cours"))))
A16: US-013 | B16: EP-02 | C16: Corriger un numéro de châssis avec validation d'un collègue | D16: Motif ; ancien numéro trouvable ; refus si facturé | E16: Partiel | F16: =COUNTIF('Plan de test'!$C$5:$C$152,"*"&A16&"*") | G16: =COUNTIFS('Plan de test'!$C$5:$C$152,"*"&A16&"*",'Plan de test'!$M$5:$M$152,"Réussi") | H16: =COUNTIFS('Plan de test'!$C$5:$C$152,"*"&A16&"*",'Plan de test'!$M$5:$M$152,"Échec")+COUNTIFS('Plan de test'!$C$5:$C$152,"*"&A16&"*",'Plan de test'!$M$5:$M$152,"Bloqué") | I16: =F16-G16-H16-COUNTIFS('Plan de test'!$C$5:$C$152,"*"&A16&"*",'Plan de test'!$M$5:$M$152,"Non livré") | J16: =IF(F16=0,"Aucun cas",IF(H16>0,"Échec",IF(G16=F16,"Validée",IF(G16+COUNTIFS('Plan de test'!$C$5:$C$152,"*"&A16&"*",'Plan de test'!$M$5:$M$152,"Non livré")=F16,"Non livrée","En cours")))) | K16: Règle « facturé » au lot 2
A17: US-020 | B17: EP-03 | C17: Créer une commande fournisseur | D17: Le stock ne change pas ; statut COMMANDÉE | E17: Livré | F17: =COUNTIF('Plan de test'!$C$5:$C$152,"*"&A17&"*") | G17: =COUNTIFS('Plan de test'!$C$5:$C$152,"*"&A17&"*",'Plan de test'!$M$5:$M$152,"Réussi") | H17: =COUNTIFS('Plan de test'!$C$5:$C$152,"*"&A17&"*",'Plan de test'!$M$5:$M$152,"Échec")+COUNTIFS('Plan de test'!$C$5:$C$152,"*"&A17&"*",'Plan de test'!$M$5:$M$152,"Bloqué") | I17: =F17-G17-H17-COUNTIFS('Plan de test'!$C$5:$C$152,"*"&A17&"*",'Plan de test'!$M$5:$M$152,"Non livré") | J17: =IF(F17=0,"Aucun cas",IF(H17>0,"Échec",IF(G17=F17,"Validée",IF(G17+COUNTIFS('Plan de test'!$C$5:$C$152,"*"&A17&"*",'Plan de test'!$M$5:$M$152,"Non livré")=F17,"Non livrée","En cours"))))
A18: US-021 | B18: EP-03 | C18: Faire avancer le dossier d'étape en étape | D18: Date et auteur de chaque étape ; étape sautée refusée | E18: Livré | F18: =COUNTIF('Plan de test'!$C$5:$C$152,"*"&A18&"*") | G18: =COUNTIFS('Plan de test'!$C$5:$C$152,"*"&A18&"*",'Plan de test'!$M$5:$M$152,"Réussi") | H18: =COUNTIFS('Plan de test'!$C$5:$C$152,"*"&A18&"*",'Plan de test'!$M$5:$M$152,"Échec")+COUNTIFS('Plan de test'!$C$5:$C$152,"*"&A18&"*",'Plan de test'!$M$5:$M$152,"Bloqué") | I18: =F18-G18-H18-COUNTIFS('Plan de test'!$C$5:$C$152,"*"&A18&"*",'Plan de test'!$M$5:$M$152,"Non livré") | J18: =IF(F18=0,"Aucun cas",IF(H18>0,"Échec",IF(G18=F18,"Validée",IF(G18+COUNTIFS('Plan de test'!$C$5:$C$152,"*"&A18&"*",'Plan de test'!$M$5:$M$152,"Non livré")=F18,"Non livrée","En cours"))))
A19: US-022 | B19: EP-03 | C19: Saisir les frais d'un arrivage avec leurs pièces | D19: Frais sans pièce signalé ; coût provisoire recalculé | E19: Livré | F19: =COUNTIF('Plan de test'!$C$5:$C$152,"*"&A19&"*") | G19: =COUNTIFS('Plan de test'!$C$5:$C$152,"*"&A19&"*",'Plan de test'!$M$5:$M$152,"Réussi") | H19: =COUNTIFS('Plan de test'!$C$5:$C$152,"*"&A19&"*",'Plan de test'!$M$5:$M$152,"Échec")+COUNTIFS('Plan de test'!$C$5:$C$152,"*"&A19&"*",'Plan de test'!$M$5:$M$152,"Bloqué") | I19: =F19-G19-H19-COUNTIFS('Plan de test'!$C$5:$C$152,"*"&A19&"*",'Plan de test'!$M$5:$M$152,"Non livré") | J19: =IF(F19=0,"Aucun cas",IF(H19>0,"Échec",IF(G19=F19,"Validée",IF(G19+COUNTIFS('Plan de test'!$C$5:$C$152,"*"&A19&"*",'Plan de test'!$M$5:$M$152,"Non livré")=F19,"Non livrée","En cours"))))
A20: US-023 | B20: EP-03 | C20: Importer la liste de colisage | D20: Châssis EN TRANSIT FOURNISSEUR ; doublons rejetés avec leur ligne | E20: Livré | F20: =COUNTIF('Plan de test'!$C$5:$C$152,"*"&A20&"*") | G20: =COUNTIFS('Plan de test'!$C$5:$C$152,"*"&A20&"*",'Plan de test'!$M$5:$M$152,"Réussi") | H20: =COUNTIFS('Plan de test'!$C$5:$C$152,"*"&A20&"*",'Plan de test'!$M$5:$M$152,"Échec")+COUNTIFS('Plan de test'!$C$5:$C$152,"*"&A20&"*",'Plan de test'!$M$5:$M$152,"Bloqué") | I20: =F20-G20-H20-COUNTIFS('Plan de test'!$C$5:$C$152,"*"&A20&"*",'Plan de test'!$M$5:$M$152,"Non livré") | J20: =IF(F20=0,"Aucun cas",IF(H20>0,"Échec",IF(G20=F20,"Validée",IF(G20+COUNTIFS('Plan de test'!$C$5:$C$152,"*"&A20&"*",'Plan de test'!$M$5:$M$152,"Non livré")=F20,"Non livrée","En cours"))))
A21: US-024 | B21: EP-03 | C21: Scanner les châssis reçus avec son téléphone | D21: Doublon, format, modèle inattendu signalés ; compteur à jour | E21: Partiel | F21: =COUNTIF('Plan de test'!$C$5:$C$152,"*"&A21&"*") | G21: =COUNTIFS('Plan de test'!$C$5:$C$152,"*"&A21&"*",'Plan de test'!$M$5:$M$152,"Réussi") | H21: =COUNTIFS('Plan de test'!$C$5:$C$152,"*"&A21&"*",'Plan de test'!$M$5:$M$152,"Échec")+COUNTIFS('Plan de test'!$C$5:$C$152,"*"&A21&"*",'Plan de test'!$M$5:$M$152,"Bloqué") | I21: =F21-G21-H21-COUNTIFS('Plan de test'!$C$5:$C$152,"*"&A21&"*",'Plan de test'!$M$5:$M$152,"Non livré") | J21: =IF(F21=0,"Aucun cas",IF(H21>0,"Échec",IF(G21=F21,"Validée",IF(G21+COUNTIFS('Plan de test'!$C$5:$C$152,"*"&A21&"*",'Plan de test'!$M$5:$M$152,"Non livré")=F21,"Non livrée","En cours")))) | K21: Saisie clavier/lecteur livrée ; caméra à venir
A22: US-025 | B22: EP-03 | C22: Valider la réception | D22: Stock inchangé avant, +N après ; PV généré | E22: Livré | F22: =COUNTIF('Plan de test'!$C$5:$C$152,"*"&A22&"*") | G22: =COUNTIFS('Plan de test'!$C$5:$C$152,"*"&A22&"*",'Plan de test'!$M$5:$M$152,"Réussi") | H22: =COUNTIFS('Plan de test'!$C$5:$C$152,"*"&A22&"*",'Plan de test'!$M$5:$M$152,"Échec")+COUNTIFS('Plan de test'!$C$5:$C$152,"*"&A22&"*",'Plan de test'!$M$5:$M$152,"Bloqué") | I22: =F22-G22-H22-COUNTIFS('Plan de test'!$C$5:$C$152,"*"&A22&"*",'Plan de test'!$M$5:$M$152,"Non livré") | J22: =IF(F22=0,"Aucun cas",IF(H22>0,"Échec",IF(G22=F22,"Validée",IF(G22+COUNTIFS('Plan de test'!$C$5:$C$152,"*"&A22&"*",'Plan de test'!$M$5:$M$152,"Non livré")=F22,"Non livrée","En cours"))))
A23: US-026 | B23: EP-03 | C23: Recevoir un arrivage en plusieurs fois | D23: RÉCEPTION PARTIELLE ; reliquat ; seconde réception | E23: Livré | F23: =COUNTIF('Plan de test'!$C$5:$C$152,"*"&A23&"*") | G23: =COUNTIFS('Plan de test'!$C$5:$C$152,"*"&A23&"*",'Plan de test'!$M$5:$M$152,"Réussi") | H23: =COUNTIFS('Plan de test'!$C$5:$C$152,"*"&A23&"*",'Plan de test'!$M$5:$M$152,"Échec")+COUNTIFS('Plan de test'!$C$5:$C$152,"*"&A23&"*",'Plan de test'!$M$5:$M$152,"Bloqué") | I23: =F23-G23-H23-COUNTIFS('Plan de test'!$C$5:$C$152,"*"&A23&"*",'Plan de test'!$M$5:$M$152,"Non livré") | J23: =IF(F23=0,"Aucun cas",IF(H23>0,"Échec",IF(G23=F23,"Validée",IF(G23+COUNTIFS('Plan de test'!$C$5:$C$152,"*"&A23&"*",'Plan de test'!$M$5:$M$152,"Non livré")=F23,"Non livrée","En cours"))))
A24: US-027 | B24: EP-03 | C24: Signaler une moto endommagée à la réception | D24: Entre BLOQUÉE avec sa photo ; non proposée à la vente | E24: Partiel | F24: =COUNTIF('Plan de test'!$C$5:$C$152,"*"&A24&"*") | G24: =COUNTIFS('Plan de test'!$C$5:$C$152,"*"&A24&"*",'Plan de test'!$M$5:$M$152,"Réussi") | H24: =COUNTIFS('Plan de test'!$C$5:$C$152,"*"&A24&"*",'Plan de test'!$M$5:$M$152,"Échec")+COUNTIFS('Plan de test'!$C$5:$C$152,"*"&A24&"*",'Plan de test'!$M$5:$M$152,"Bloqué") | I24: =F24-G24-H24-COUNTIFS('Plan de test'!$C$5:$C$152,"*"&A24&"*",'Plan de test'!$M$5:$M$152,"Non livré") | J24: =IF(F24=0,"Aucun cas",IF(H24>0,"Échec",IF(G24=F24,"Validée",IF(G24+COUNTIFS('Plan de test'!$C$5:$C$152,"*"&A24&"*",'Plan de test'!$M$5:$M$152,"Non livré")=F24,"Non livrée","En cours")))) | K24: Motif texte livré ; photo avec le module Documents
A25: US-040 | B25: EP-05 | C25: Voir le stock physique, réservé, disponible, bloqué et en transit par modèle | D25: 100 physiques dont 20 réservées : 80 disponibles | E25: Livré | F25: =COUNTIF('Plan de test'!$C$5:$C$152,"*"&A25&"*") | G25: =COUNTIFS('Plan de test'!$C$5:$C$152,"*"&A25&"*",'Plan de test'!$M$5:$M$152,"Réussi") | H25: =COUNTIFS('Plan de test'!$C$5:$C$152,"*"&A25&"*",'Plan de test'!$M$5:$M$152,"Échec")+COUNTIFS('Plan de test'!$C$5:$C$152,"*"&A25&"*",'Plan de test'!$M$5:$M$152,"Bloqué") | I25: =F25-G25-H25-COUNTIFS('Plan de test'!$C$5:$C$152,"*"&A25&"*",'Plan de test'!$M$5:$M$152,"Non livré") | J25: =IF(F25=0,"Aucun cas",IF(H25>0,"Échec",IF(G25=F25,"Validée",IF(G25+COUNTIFS('Plan de test'!$C$5:$C$152,"*"&A25&"*",'Plan de test'!$M$5:$M$152,"Non livré")=F25,"Non livrée","En cours"))))
A26: US-041 | B26: EP-05 | C26: Voir le stock global consolidé | D26: Transit compté une fois ; total = somme des emplacements | E26: Livré | F26: =COUNTIF('Plan de test'!$C$5:$C$152,"*"&A26&"*") | G26: =COUNTIFS('Plan de test'!$C$5:$C$152,"*"&A26&"*",'Plan de test'!$M$5:$M$152,"Réussi") | H26: =COUNTIFS('Plan de test'!$C$5:$C$152,"*"&A26&"*",'Plan de test'!$M$5:$M$152,"Échec")+COUNTIFS('Plan de test'!$C$5:$C$152,"*"&A26&"*",'Plan de test'!$M$5:$M$152,"Bloqué") | I26: =F26-G26-H26-COUNTIFS('Plan de test'!$C$5:$C$152,"*"&A26&"*",'Plan de test'!$M$5:$M$152,"Non livré") | J26: =IF(F26=0,"Aucun cas",IF(H26>0,"Échec",IF(G26=F26,"Validée",IF(G26+COUNTIFS('Plan de test'!$C$5:$C$152,"*"&A26&"*",'Plan de test'!$M$5:$M$152,"Non livré")=F26,"Non livrée","En cours"))))
A27: US-042 | B27: EP-05 | C27: Bloquer un châssis en litige | D27: Motif et pièce obligatoires ; non proposé à la vente ; déblocage tracé | E27: Partiel | F27: =COUNTIF('Plan de test'!$C$5:$C$152,"*"&A27&"*") | G27: =COUNTIFS('Plan de test'!$C$5:$C$152,"*"&A27&"*",'Plan de test'!$M$5:$M$152,"Réussi") | H27: =COUNTIFS('Plan de test'!$C$5:$C$152,"*"&A27&"*",'Plan de test'!$M$5:$M$152,"Échec")+COUNTIFS('Plan de test'!$C$5:$C$152,"*"&A27&"*",'Plan de test'!$M$5:$M$152,"Bloqué") | I27: =F27-G27-H27-COUNTIFS('Plan de test'!$C$5:$C$152,"*"&A27&"*",'Plan de test'!$M$5:$M$152,"Non livré") | J27: =IF(F27=0,"Aucun cas",IF(H27>0,"Échec",IF(G27=F27,"Validée",IF(G27+COUNTIFS('Plan de test'!$C$5:$C$152,"*"&A27&"*",'Plan de test'!$M$5:$M$152,"Non livré")=F27,"Non livrée","En cours")))) | K27: Pièce = référence texte ; dépôt de fichier avec le module Documents
A28: US-043 | B28: EP-05 | C28: Créer puis expédier un transfert vers une boutique | D28: Création sans mouvement ; expédition : stock source −N, EN TRANSIT INTERNE | E28: Livré | F28: =COUNTIF('Plan de test'!$C$5:$C$152,"*"&A28&"*") | G28: =COUNTIFS('Plan de test'!$C$5:$C$152,"*"&A28&"*",'Plan de test'!$M$5:$M$152,"Réussi") | H28: =COUNTIFS('Plan de test'!$C$5:$C$152,"*"&A28&"*",'Plan de test'!$M$5:$M$152,"Échec")+COUNTIFS('Plan de test'!$C$5:$C$152,"*"&A28&"*",'Plan de test'!$M$5:$M$152,"Bloqué") | I28: =F28-G28-H28-COUNTIFS('Plan de test'!$C$5:$C$152,"*"&A28&"*",'Plan de test'!$M$5:$M$152,"Non livré") | J28: =IF(F28=0,"Aucun cas",IF(H28>0,"Échec",IF(G28=F28,"Validée",IF(G28+COUNTIFS('Plan de test'!$C$5:$C$152,"*"&A28&"*",'Plan de test'!$M$5:$M$152,"Non livré")=F28,"Non livrée","En cours"))))
A29: US-044 | B29: EP-05 | C29: Réceptionner un transfert par scan | D29: Stock destination +pointés ; manquant en transit et A12 ; non prévu refusé | E29: Livré | F29: =COUNTIF('Plan de test'!$C$5:$C$152,"*"&A29&"*") | G29: =COUNTIFS('Plan de test'!$C$5:$C$152,"*"&A29&"*",'Plan de test'!$M$5:$M$152,"Réussi") | H29: =COUNTIFS('Plan de test'!$C$5:$C$152,"*"&A29&"*",'Plan de test'!$M$5:$M$152,"Échec")+COUNTIFS('Plan de test'!$C$5:$C$152,"*"&A29&"*",'Plan de test'!$M$5:$M$152,"Bloqué") | I29: =F29-G29-H29-COUNTIFS('Plan de test'!$C$5:$C$152,"*"&A29&"*",'Plan de test'!$M$5:$M$152,"Non livré") | J29: =IF(F29=0,"Aucun cas",IF(H29>0,"Échec",IF(G29=F29,"Validée",IF(G29+COUNTIFS('Plan de test'!$C$5:$C$152,"*"&A29&"*",'Plan de test'!$M$5:$M$152,"Non livré")=F29,"Non livrée","En cours"))))
A30: US-045 | B30: EP-05 | C30: Être alerté d'un transfert non réceptionné | D30: Alerte après le délai paramétré | E30: Livré | F30: =COUNTIF('Plan de test'!$C$5:$C$152,"*"&A30&"*") | G30: =COUNTIFS('Plan de test'!$C$5:$C$152,"*"&A30&"*",'Plan de test'!$M$5:$M$152,"Réussi") | H30: =COUNTIFS('Plan de test'!$C$5:$C$152,"*"&A30&"*",'Plan de test'!$M$5:$M$152,"Échec")+COUNTIFS('Plan de test'!$C$5:$C$152,"*"&A30&"*",'Plan de test'!$M$5:$M$152,"Bloqué") | I30: =F30-G30-H30-COUNTIFS('Plan de test'!$C$5:$C$152,"*"&A30&"*",'Plan de test'!$M$5:$M$152,"Non livré") | J30: =IF(F30=0,"Aucun cas",IF(H30>0,"Échec",IF(G30=F30,"Validée",IF(G30+COUNTIFS('Plan de test'!$C$5:$C$152,"*"&A30&"*",'Plan de test'!$M$5:$M$152,"Non livré")=F30,"Non livrée","En cours"))))
A31: US-046 | B31: EP-05 | C31: Consulter le stock à une date passée | D31: Stock reconstitué égal au stock de fin de période | E31: À livrer | F31: =COUNTIF('Plan de test'!$C$5:$C$152,"*"&A31&"*") | G31: =COUNTIFS('Plan de test'!$C$5:$C$152,"*"&A31&"*",'Plan de test'!$M$5:$M$152,"Réussi") | H31: =COUNTIFS('Plan de test'!$C$5:$C$152,"*"&A31&"*",'Plan de test'!$M$5:$M$152,"Échec")+COUNTIFS('Plan de test'!$C$5:$C$152,"*"&A31&"*",'Plan de test'!$M$5:$M$152,"Bloqué") | I31: =F31-G31-H31-COUNTIFS('Plan de test'!$C$5:$C$152,"*"&A31&"*",'Plan de test'!$M$5:$M$152,"Non livré") | J31: =IF(F31=0,"Aucun cas",IF(H31>0,"Échec",IF(G31=F31,"Validée",IF(G31+COUNTIFS('Plan de test'!$C$5:$C$152,"*"&A31&"*",'Plan de test'!$M$5:$M$152,"Non livré")=F31,"Non livrée","En cours")))) | K31: Prévu avec les rapports
A32: US-155 | B32: EP-12 | C32: Garantie qu'aucune opération sensible ne se supprime | D32: Aucun bouton Supprimer ; suppression par API refusée | E32: Livré | F32: =COUNTIF('Plan de test'!$C$5:$C$152,"*"&A32&"*") | G32: =COUNTIFS('Plan de test'!$C$5:$C$152,"*"&A32&"*",'Plan de test'!$M$5:$M$152,"Réussi") | H32: =COUNTIFS('Plan de test'!$C$5:$C$152,"*"&A32&"*",'Plan de test'!$M$5:$M$152,"Échec")+COUNTIFS('Plan de test'!$C$5:$C$152,"*"&A32&"*",'Plan de test'!$M$5:$M$152,"Bloqué") | I32: =F32-G32-H32-COUNTIFS('Plan de test'!$C$5:$C$152,"*"&A32&"*",'Plan de test'!$M$5:$M$152,"Non livré") | J32: =IF(F32=0,"Aucun cas",IF(H32>0,"Échec",IF(G32=F32,"Validée",IF(G32+COUNTIFS('Plan de test'!$C$5:$C$152,"*"&A32&"*",'Plan de test'!$M$5:$M$152,"Non livré")=F32,"Non livrée","En cours")))) | K32: Vérifié sur les opérations du lot 1

Sheet Tests automatiques
A1: Tests automatiques de l'équipe (JUnit)
A2: Ils s'exécutent sur une base PostgreSQL réelle (conteneur) à chaque livraison : mvn test. Ils couvrent règles de gestion, droits et périmètre par appel direct à l'API.
A4: Classe de test | B4: Domaine | C4: Tests | D4: Cas du plan couverts | E4: Ce qu'elle vérifie
A5: VitracosarlApiApplicationTests | B5: TRV | C5: 1 | D5: TC-TRV-008 | E5: Context loads
A6: ArrivagesTest | B6: APP | C6: 9 | D6: TC-APP-003, 005, 006, 007 | E6: Un arrivage se cree apres la confirmation avec ses dates et son retard se mesure; Les arrivages commandent les etapes de la commande; Le dedouanement avance sans sauter et sans arrivee ni retrait de la date …
A7: AuthEtUtilisateursTest | B7: ADM | C7: 15 | D7: TC-ADM-001, 003, 004, 006, 021 | E7: L'administrateur amorce se connecte et recoit ses permissions; L'etat de connexion survit entre les requetes et prend fin ala deconnexion; Un mauvais mot de passe et un email inconnu donnent la meme reponse …
A8: CatalogueTest | B8: CAT | C8: 9 | D8: TC-CAT-001, 002, 003, 005 | E8: Un modele se cree avec ses prix initiaux et son code article est unique; Le catalogue se liste se filtre et se lit sans droit decriture; Le prix dachat nest jamais envoye sans la permission …
A9: ChassisTest | B9: CAT | C9: 12 | D9: TC-CAT-005, 006, 007, 009, 010, TC-TRV-001, 002 | E9: Un chassis se normalise se controle et se journalise; Un doublon est refuse avec lemplacement du chassis existant; Le format du modele les statuts initiaux et lemplacement sont controles …
A10: CommandesFournisseurTest | B10: APP | C10: 10 | D10: TC-APP-001, 002, 003, 004, 008 | E10: Une commande se cree numerotee avec ses totaux et ne touche pas au stock; Les prix sont masques au magasin qui voit seulement les quantites; Le fournisseur la devise le taux et les lignes sont controles …
A11: DoubleAuthentificationTest | B11: ADM | C11: 11 | D11: TC-ADM-005 | E11: Un role qui exige le second facteur le fait configurer ala premiere connexion; Ensuite la connexion exige un code valide et ne se rejoue pas; Un code de secours ouvre une session une seule fois …
A12: EmplacementsTest | B12: ADM | C12: 12 | D12: TC-ADM-009, 010 | E12: L'emplacement transit est cree par le systeme et intouchable; Un magasin et une boutique se creent et le code est unique; Le type depot et transit ne se cree pas ala main …
A13: NotificationsParEmailTest | B13: ADM | C13: 1 | D13: TC-ADM-017 | E13: La direction recoit par email le changement de droits avec le lien de lecran
A14: NotificationsTest | B14: ADM | C14: 8 | D14: TC-ADM-015, 016 | E14: Un changement de roles notifie la direction avec ancien nouveau et auteur; La creation dun compte notifie aussi la direction; Un changement de droits dun role donne les permissions ajoutees et retirees …
A15: NumerotationServiceTest | B15: ADM | C15: 6 | D15: TC-ADM-014 | E15: Le numero porte le prefixe lemplacement lannee et un compteur sur six chiffres; Un document sans emplacement ne contient pas de segment emplacement; Les compteurs sont independants par type et par emplacement …
A16: ReceptionsTest | B16: REC | C16: 6 | D16: TC-REC-001 à 008, 011 | E16: Une reception nouvre pas tant que larrivage nest pas dedouane ni hors du magasin ou du perimetre; Chaque scan est controle et le rapprochement se met ajour sans toucher au stock; La validation par un second utilisateur fait entrer les motos en stock et met la commande ajour …
... A27: SecuriteTest | B27: TRV | C27: 4 | D27: TC-ADM-021, TC-TRV-004 | E27: L'etat de sante est public et verifie la base; Tout le reste exige une authentification; Une ecriture sans jeton csrf est refusee …
A28: Total | C28: =SUM(C5:C27)
A30: Détail : chaque test
A31: Classe de test | B31: Domaine | C31: N° | D31: Test | E31: Énoncé
A32: VitracosarlApiApplicationTests | B32: TRV | C32: 1 | D32: contextLoads | E32: Context loads
A33: ArrivagesTest | B33: APP | C33: 1 | D33: unArrivageSeCreeApresLaConfirmationAvecSesDatesEtSonRetardSeMesure | E33: Un arrivage se cree apres la confirmation avec ses dates et son retard se mesure
A34: ArrivagesTest | B34: APP | C34: 2 | D34: lesArrivagesCommandentLesEtapesDeLaCommande | E34: Les arrivages commandent les etapes de la commande
A35: ArrivagesTest | B35: APP | C35: 3 | D35: leDedouanementAvanceSansSauterEtSansArriveeNiRetraitDeLaDate | E35: Le dedouanement avance sans sauter et sans arrivee ni retrait de la date
A36: ArrivagesTest | B36: APP | C36: 4 | D36: lesFraisPortentDeviseTauxEtPieceEtAlimententLeCoutDeRevientProvisoire | E36: Les frais portent devise taux et piece et alimentent le cout de revient provisoire
A37: ArrivagesTest | B37: APP | C37: 5 | D37: lesFraisSontDesElementsDuCoutDeRevientDoncMasquesAuMagasin | E37: Les frais sont des elements du cout de revient donc masques au magasin
A38: ArrivagesTest | B38: APP | C38: 6 | D38: leColisageCsvCreeLesChassisAnnoncesEtRejetteLesLignesFautivesAvecLeurMotif | E38: Le colisage csv cree les chassis annonces et rejette les lignes fautives avec leur motif
A39: ArrivagesTest | B39: APP | C39: 7 | D39: leColisageAccepteLesExportsExcelFrancaisCommeLesFichiersXlsxEtRefuseLeReste | E39: Le colisage accepte les exports excel francais comme les fichiers xlsx et refuse le reste
A40: ArrivagesTest | B40: APP | C40: 8 | D40: leDedouanementTermineFaitPasserLesChassisAReceptionnerEtPrevientLeMagasin | E40: Le dedouanement termine fait passer les chassis areceptionner et previent le magasin
A41: ArrivagesTest | B41: APP | C41: 9 | D41: laQuantiteCommandeeSeCumuleSurLesArrivagesDUneMemeCommande | E41: La quantite commandee se cumule sur les arrivages dune meme commande
A42: AuthEtUtilisateursTest | B42: ADM | C42: 1 | D42: lAdministrateurAmorceSeConnecteEtRecoitSesPermissions | E42: L'administrateur amorce se connecte et recoit ses permissions
A43: AuthEtUtilisateursTest | B43: ADM | C43: 2 | D43: lEtatDeConnexionSurvitEntreLesRequetesEtPrendFinALaDeconnexion | E43: L'etat de connexion survit entre les requetes et prend fin ala deconnexion
... A189: SecuriteTest | B189: TRV | C189: 4 | D189: leFrontAutoriseEstAccepteAvecSesCookiesEtUneOrigineInconnueRefusee | E189: Le front autorise est accepte avec ses cookies et une origine inconnue refusee

Sheet Comptes de test
A1: Comptes de test à créer sur l'environnement de recette
A2: Un compte par profil, avec une adresse de test. Aucun mot de passe n'est consigné ici : chaque compte choisit le sien à l'activation (lien reçu par e-mail).
A4: Profil | B4: Rôle livré | C4: Périmètre | D4: Second facteur | E4: Usage principal en recette | F4: Droits clés | G4: Adresse e-mail du compte | H4: Créé le
A5: Administrateur | B5: admin | C5: Global | D5: Oui (obligatoire) | E5: Paramétrage, rôles, import du stock initial | F5: administration : tout ; stock : importer ; catalogue : tout
A6: Direction | B6: direction | C6: Global | D6: Oui (obligatoire) | E6: Vues consolidées, validations, retour arrière de commande | F6: validations V ; prix d'achat ; stock : bloquer ; retour arrière
A7: Responsable commercial | B7: responsable_commercial | C7: Selon affectation | D7: Non | E7: Catalogue et prix, clients | F7: catalogue : C ; clients, commandes : CV
A8: Commercial | B8: commercial | C8: Ses emplacements | D8: Non | E8: Tableau de bord Commercial, consultation du stock | F8: stock : voir ; pas de prix d'achat
A9: Comptabilité / Caisse | B9: comptabilite_caisse | C9: Selon affectation | D9: Oui (obligatoire) | E9: Coûts, factures (lots suivants) | F9: prix d'achat ; coût de revient : CV ; exports
A10: Magasin (responsable) | B10: magasin | C10: Son magasin | D10: Non | E10: Réceptions, transferts, blocage, pointage d'ouverture | F10: réceptions : CV ; transferts : CV ; stock : modifier, bloquer ; inventaires : C
A11: Magasin (second utilisateur) | B11: magasin | C11: Son magasin | D11: Non | E11: Seconde validation (réception, correction de numéro) | F11: idem Magasin : indispensable pour la séparation des tâches
A12: Contrôleur | B12: controleur | C12: Selon affectation | D12: Non | E12: Alertes, anomalies, blocage, corrections de numéro | F12: lecture large ; stock : modifier, bloquer ; inventaires : C ; anomalies : CV
A13: Boutique | B13: boutique | C13: Sa boutique | D13: Non | E13: Réception de transferts, pointage d'ouverture | F13: transferts : C ; stock : voir ; inventaires : C
A14: Acheteur (rôle personnalisé) | B14: acheteur | C14: Global | D14: Non | E14: Commandes fournisseur, arrivages, colisage, frais | F14: approvisionnements : tout ; prix d'achat : voir ; retour arrière (optionnel)
A15: Compte des deux sites | B15: magasin | C15: Magasin et boutique | D15: Non | E15: Tests de séparation expéditeur/réceptionnaire (TC-TRF-005) | F15: idem Magasin, avec les deux emplacements
A17: Prévoir au minimum : 2 comptes « Magasin » sur le même magasin (séparation des tâches), 1 compte « Boutique » par boutique, 1 compte « Magasin » rattaché aux deux sites, 1 contrôleur (destinataire des alertes).
A18: Les rôles Administrateur, Direction et Comptabilité exigent le second facteur : prévoir une application d'authentification sur le téléphone de chaque testeur concerné et conserver les codes de secours.
A19: Données de base à créer avant les tests : un magasin, deux boutiques, un fournisseur, deux modèles avec prix et format de châssis, un acheteur (rôle personnalisé avec les droits d'approvisionnement).

Sheet Anomalies
A1: Suivi des anomalies de recette
A2: Une ligne par anomalie. Gravité : Bloquante (empêche de continuer), Majeure (fonction essentielle fausse), Mineure (confort, libellé, ergonomie).
A4: N° | B4: Date | C4: Cas de test | D4: Gravité | E4: Description | F4: Étapes pour reproduire / preuve | G4: Statut | H4: Assignée à | I4: Version | J4: Date de correction | K4: Retest (résultat) | L4: Commentaire
A5: ANO-001
A6: ANO-002
A7: ANO-003
A8: ANO-004
A9: ANO-005
A10: ANO-006
A11: ANO-007
A12: ANO-008
A13: ANO-009
A14: ANO-010
A15: ANO-011
A16: ANO-012
... A64: ANO-060
